Workbook

Sheet 🎯 Dashboard
A1: 🎯 DASHBOARD — Resumen Ejecutivo de Inventario
B3: 📦 TOTAL REFERENCIAS | G3: 🟢 PRODUCTOS EN STOCK OK | L3: 🟠 STOCK BAJO MÍNIMO | Q3: 🔴 SIN STOCK
B4: =COUNTA('📦 Maestro Productos'!A4:A1000) -> 20 | G4: =COUNTIF('📊 Stock Actual'!L4:L100,"🟢 OK") -> 20 | L4: =COUNTIF('📊 Stock Actual'!L4:L100,"🟠 STOCK BAJO") -> 0 | Q4: =COUNTIF('📊 Stock Actual'!L4:L100,"🔴 SIN STOCK") -> 0
B7: 📥 ENTRADAS HOY (€) | G7: 📤 SALIDAS HOY (€) | L7: 📥 ENTRADAS MES (€) | Q7: 📤 SALIDAS MES (€)
B8: =SUMIF('📥 Entradas'!H4:H500,TODAY(),'📥 Entradas'!G4:G500) -> 0 | G8: =SUMIF('📤 Salidas'!H4:H500,TODAY(),'📤 Salidas'!G4:G500) -> 0 | L8: =SUMPRODUCT((MONTH('📥 Entradas'!H4:H500)=MONTH(TODAY()))*(YEAR('📥 Entradas'!H4:H500)=YEAR(TODAY())),'📥 Entradas'!G4:G500) -> 0 | Q8: =SUMPRODUCT((MONTH('📤 Salidas'!H4:H500)=MONTH(TODAY()))*(YEAR('📤 Salidas'!H4:H500)=YEAR(TODAY())),'📤 Salidas'!G4:G500) -> 0
B12: ⚠️ ALERTAS DE STOCK — Productos que requieren atención
B13: REF | C13: Descripción | F13: Stock Actual | H13: Stock Mínimo | J13: Diferencia | L13: Estado | N13: Acción Recomendada
B14: ='📊 Stock Actual'!A14 -> CAL-001 | C14: ='📊 Stock Actual'!B14 -> Caldera Gas Condensación 24kW | F14: ='📊 Stock Actual'!H14 -> 6 | H14: ='📊 Stock Actual'!I14 -> 3 | J14: =F14-H14 -> 3 | L14: ='📊 Stock Actual'!L14 -> 🟢 OK | N14: =IF(F14<=0,"🚨 Pedir urgente",IF(F14<=H14,"📋 Revisar pedido","✅ Sin acción")) -> ✅ Sin acción
B15: ='📊 Stock Actual'!A15 -> CAL-002 | C15: ='📊 Stock Actual'!B15 -> Radiador Aluminio 10 Elem. | F15: ='📊 Stock Actual'!H15 -> 45 | H15: ='📊 Stock Actual'!I15 -> 20 | J15: =F15-H15 -> 25 | L15: ='📊 Stock Actual'!L15 -> 🟢 OK | N15: =IF(F15<=0,"🚨 Pedir urgente",IF(F15<=H15,"📋 Revisar pedido","✅ Sin acción")) -> ✅ Sin acción
B16: ='📊 Stock Actual'!A16 -> CAB-001 | C16: ='📊 Stock Actual'!B16 -> Cable Solar 4mm² (m) | F16: ='📊 Stock Actual'!H16 -> 1450 | H16: ='📊 Stock Actual'!I16 -> 500 | J16: =F16-H16 -> 950 | L16: ='📊 Stock Actual'!L16 -> 🟢 OK | N16: =IF(F16<=0,"🚨 Pedir urgente",IF(F16<=H16,"📋 Revisar pedido","✅ Sin acción")) -> ✅ Sin acción
B17: ='📊 Stock Actual'!A17 -> CAB-002 | C17: ='📊 Stock Actual'!B17 -> Cable Solar 6mm² (m) | F17: ='📊 Stock Actual'!H17 -> 800 | H17: ='📊 Stock Actual'!I17 -> 500 | J17: =F17-H17 -> 300 | L17: ='📊 Stock Actual'!L17 -> 🟢 OK | N17: =IF(F17<=0,"🚨 Pedir urgente",IF(F17<=H17,"📋 Revisar pedido","✅ Sin acción")) -> ✅ Sin acción
B18: ='📊 Stock Actual'!A18 -> EST-001 | C18: ='📊 Stock Actual'!B18 -> Estructura Tejado Inclinado (kit) | F18: ='📊 Stock Actual'!H18 -> 20 | H18: ='📊 Stock Actual'!I18 -> 10 | J18: =F18-H18 -> 10 | L18: ='📊 Stock Actual'!L18 -> 🟢 OK | N18: =IF(F18<=0,"🚨 Pedir urgente",IF(F18<=H18,"📋 Revisar pedido","✅ Sin acción")) -> ✅ Sin acción
B19: ='📊 Stock Actual'!A19 -> EST-002 | C19: ='📊 Stock Actual'!B19 -> Estructura Cubierta Plana (kit) | F19: ='📊 Stock Actual'!H19 -> 18 | H19: ='📊 Stock Actual'!I19 -> 5 | J19: =F19-H19 -> 13 | L19: ='📊 Stock Actual'!L19 -> 🟢 OK | N19: =IF(F19<=0,"🚨 Pedir urgente",IF(F19<=H19,"📋 Revisar pedido","✅ Sin acción")) -> ✅ Sin acción
B20: ='📊 Stock Actual'!A20 -> PRO-001 | C20: ='📊 Stock Actual'!B20 -> Protección DC 1000V 2P | F20: ='📊 Stock Actual'!H20 -> 60 | H20: ='📊 Stock Actual'!I20 -> 20 | J20: =F20-H20 -> 40 | L20: ='📊 Stock Actual'!L20 -> 🟢 OK | N20: =IF(F20<=0,"🚨 Pedir urgente",IF(F20<=H20,"📋 Revisar pedido","✅ Sin acción")) -> ✅ Sin acción
B21: ='📊 Stock Actual'!A21 -> PRO-002 | C21: ='📊 Stock Actual'!B21 -> Contador Bidireccional Smart | F21: ='📊 Stock Actual'!H21 -> 12 | H21: ='📊 Stock Actual'!I21 -> 5 | J21: =F21-H21 -> 7 | L21: ='📊 Stock Actual'!L21 -> 🟢 OK | N21: =IF(F21<=0,"🚨 Pedir urgente",IF(F21<=H21,"📋 Revisar pedido","✅ Sin acción")) -> ✅ Sin acción
B22: ='📊 Stock Actual'!A22 -> TUB-001 | C22: ='📊 Stock Actual'!B22 -> Tubo Corrugado PG29 (m) | F22: ='📊 Stock Actual'!H22 -> 600 | H22: ='📊 Stock Actual'!I22 -> 200 | J22: =F22-H22 -> 400 | L22: ='📊 Stock Actual'!L22 -> 🟢 OK | N22: =IF(F22<=0,"🚨 Pedir urgente",IF(F22<=H22,"📋 Revisar pedido","✅ Sin acción")) -> ✅ Sin acción
B23: ='📊 Stock Actual'!A23 -> TUB-002 | C23: ='📊 Stock Actual'!B23 -> Tubería Cobre 22mm (m) | F23: ='📊 Stock Actual'!H23 -> 250 | H23: ='📊 Stock Actual'!I23 -> 100 | J23: =F23-H23 -> 150 | L23: ='📊 Stock Actual'!L23 -> 🟢 OK | N23: =IF(F23<=0,"🚨 Pedir urgente",IF(F23<=H23,"📋 Revisar pedido","✅ Sin acción")) -> ✅ Sin acción
B24: ='📊 Stock Actual'!A24 | C24: ='📊 Stock Actual'!B24 | F24: ='📊 Stock Actual'!H24 | H24: ='📊 Stock Actual'!I24 | J24: =F24-H24 -> 0 | L24: ='📊 Stock Actual'!L24 | N24: =IF(F24<=0,"🚨 Pedir urgente",IF(F24<=H24,"📋 Revisar pedido","✅ Sin acción")) -> 🚨 Pedir urgente
B25: ='📊 Stock Actual'!A25 | C25: ='📊 Stock Actual'!B25 | F25: ='📊 Stock Actual'!H25 | H25: ='📊 Stock Actual'!I25 | J25: =F25-H25 -> 0 | L25: ='📊 Stock Actual'!L25 | N25: =IF(F25<=0,"🚨 Pedir urgente",IF(F25<=H25,"📋 Revisar pedido","✅ Sin acción")) -> 🚨 Pedir urgente
... B33: ='📊 Stock Actual'!A33 | C33: ='📊 Stock Actual'!B33 | F33: ='📊 Stock Actual'!H33 | H33: ='📊 Stock Actual'!I33 | J33: =F33-H33 -> 0 | L33: ='📊 Stock Actual'!L33 | N33: =IF(F33<=0,"🚨 Pedir urgente",IF(F33<=H33,"📋 Revisar pedido","✅ Sin acción")) -> 🚨 Pedir urgente
B36: 💰 RESUMEN FINANCIERO DE MOVIMIENTOS
B37: Concepto | K37: Importe (€)
B38: Total Compras (Entradas) — Acumulado | K38: =SUM('📥 Entradas'!G4:G500) -> 26275
B39: Total Ventas (Salidas) — Acumulado | K39: =SUM('📤 Salidas'!G4:G500) -> 20530
B40: Margen Bruto Estimado | K40: =K39-K38 -> -5745
B41: % Margen sobre Ventas | K41: =IFERROR(K40/K39,0) -> -0.27983439

Sheet 📊 Stock Actual
A1: 📊 STOCK ACTUAL — Vista en tiempo real del inventario
A2: 🔄 Esta hoja se calcula automáticamente. Stock = Stock Inicial + Entradas - Salidas
A3: REF | B3: Descripción | C3: Categoría | D3: Unidad | E3: Stock Inicial | F3: Total Entradas | G3: Total Salidas | H3: STOCK ACTUAL | I3: Stock Mínimo | J3: Stock Máximo | K3: % Ocupación | L3: ESTADO
A4: ='📦 Maestro Productos'!A4 -> SOL-001 | B4: ='📦 Maestro Productos'!B4 -> Panel Solar Monocristalino 400W | C4: ='📦 Maestro Productos'!C4 -> Placas Solares | D4: ='📦 Maestro Productos'!E4 -> Ud. | E4: 50 | F4: =SUMIF('📥 Entradas'!$B:$B,A4,'📥 Entradas'!$E:$E) -> 30 | G4: =SUMIF('📤 Salidas'!$B:$B,A4,'📤 Salidas'!$E:$E) -> 10 | H4: =E4+F4-G4 -> 70 | I4: ='📦 Maestro Productos'!H4 -> 10 | J4: ='📦 Maestro Productos'!I4 -> 100 | K4: =IF(J4=0,"N/A",TEXT(H4/J4,"0%")) -> 70% | L4: =IF(H4<=0,"🔴 SIN STOCK",IF(H4<=I4,"🟠 STOCK BAJO","🟢 OK")) -> 🟢 OK
A5: ='📦 Maestro Productos'!A5 -> SOL-002 | B5: ='📦 Maestro Productos'!B5 -> Panel Solar Monocristalino 450W | C5: ='📦 Maestro Productos'!C5 -> Placas Solares | D5: ='📦 Maestro Productos'!E5 -> Ud. | E5: 40 | F5: =SUMIF('📥 Entradas'!$B:$B,A5,'📥 Entradas'!$E:$E) -> 20 | G5: =SUMIF('📤 Salidas'!$B:$B,A5,'📤 Salidas'!$E:$E) -> 15 | H5: =E5+F5-G5 -> 45 | I5: ='📦 Maestro Productos'!H5 -> 10 | J5: ='📦 Maestro Productos'!I5 -> 80 | K5: =IF(J5=0,"N/A",TEXT(H5/J5,"0%")) -> 56% | L5: =IF(H5<=0,"🔴 SIN STOCK",IF(H5<=I5,"🟠 STOCK BAJO","🟢 OK")) -> 🟢 OK
A6: ='📦 Maestro Productos'!A6 -> SOL-003 | B6: ='📦 Maestro Productos'!B6 -> Panel Solar Bifacial 500W | C6: ='📦 Maestro Productos'!C6 -> Placas Solares | D6: ='📦 Maestro Productos'!E6 -> Ud. | E6: 20 | F6: =SUMIF('📥 Entradas'!$B:$B,A6,'📥 Entradas'!$E:$E) -> 0 | G6: =SUMIF('📤 Salidas'!$B:$B,A6,'📤 Salidas'!$E:$E) -> 0 | H6: =E6+F6-G6 -> 20 | I6: ='📦 Maestro Productos'!H6 -> 5 | J6: ='📦 Maestro Productos'!I6 -> 50 | K6: =IF(J6=0,"N/A",TEXT(H6/J6,"0%")) -> 40% | L6: =IF(H6<=0,"🔴 SIN STOCK",IF(H6<=I6,"🟠 STOCK BAJO","🟢 OK")) -> 🟢 OK
A7: ='📦 Maestro Productos'!A7 -> INV-001 | B7: ='📦 Maestro Productos'!B7 -> Inversor Monofásico 3kW | C7: ='📦 Maestro Productos'!C7 -> Inversores | D7: ='📦 Maestro Productos'!E7 -> Ud. | E7: 8 | F7: =SUMIF('📥 Entradas'!$B:$B,A7,'📥 Entradas'!$E:$E) -> 5 | G7: =SUMIF('📤 Salidas'!$B:$B,A7,'📤 Salidas'!$E:$E) -> 2 | H7: =E7+F7-G7 -> 11 | I7: ='📦 Maestro Productos'!H7 -> 3 | J7: ='📦 Maestro Productos'!I7 -> 20 | K7: =IF(J7=0,"N/A",TEXT(H7/J7,"0%")) -> 55% | L7: =IF(H7<=0,"🔴 SIN STOCK",IF(H7<=I7,"🟠 STOCK BAJO","🟢 OK")) -> 🟢 OK
A8: ='📦 Maestro Productos'!A8 -> INV-002 | B8: ='📦 Maestro Productos'!B8 -> Inversor Monofásico 5kW | C8: ='📦 Maestro Productos'!C8 -> Inversores | D8: ='📦 Maestro Productos'!E8 -> Ud. | E8: 10 | F8: =SUMIF('📥 Entradas'!$B:$B,A8,'📥 Entradas'!$E:$E) -> 0 | G8: =SUMIF('📤 Salidas'!$B:$B,A8,'📤 Salidas'!$E:$E) -> 1 | H8: =E8+F8-G8 -> 9 | I8: ='📦 Maestro Productos'!H8 -> 3 | J8: ='📦 Maestro Productos'!I8 -> 20 | K8: =IF(J8=0,"N/A",TEXT(H8/J8,"0%")) -> 45% | L8: =IF(H8<=0,"🔴 SIN STOCK",IF(H8<=I8,"🟠 STOCK BAJO","🟢 OK")) -> 🟢 OK
A9: ='📦 Maestro Productos'!A9 -> INV-003 | B9: ='📦 Maestro Productos'!B9 -> Inversor Trifásico 10kW | C9: ='📦 Maestro Productos'!C9 -> Inversores | D9: ='📦 Maestro Productos'!E9 -> Ud. | E9: 4 | F9: =SUMIF('📥 Entradas'!$B:$B,A9,'📥 Entradas'!$E:$E) -> 0 | G9: =SUMIF('📤 Salidas'!$B:$B,A9,'📤 Salidas'!$E:$E) -> 0 | H9: =E9+F9-G9 -> 4 | I9: ='📦 Maestro Productos'!H9 -> 2 | J9: ='📦 Maestro Productos'!I9 -> 10 | K9: =IF(J9=0,"N/A",TEXT(H9/J9,"0%")) -> 40% | L9: =IF(H9<=0,"🔴 SIN STOCK",IF(H9<=I9,"🟠 STOCK BAJO","🟢 OK")) -> 🟢 OK
A10: ='📦 Maestro Productos'!A10 -> BAT-001 | B10: ='📦 Maestro Productos'!B10 -> Batería LiFePO4 5kWh | C10: ='📦 Maestro Productos'!C10 -> Baterías | D10: ='📦 Maestro Productos'!E10 -> Ud. | E10: 5 | F10: =SUMIF('📥 Entradas'!$B:$B,A10,'📥 Entradas'!$E:$E) -> 2 | G10: =SUMIF('📤 Salidas'!$B:$B,A10,'📤 Salidas'!$E:$E) -> 0 | H10: =E10+F10-G10 -> 7 | I10: ='📦 Maestro Productos'!H10 -> 2 | J10: ='📦 Maestro Productos'!I10 -> 10 | K10: =IF(J10=0,"N/A",TEXT(H10/J10,"0%")) -> 70% | L10: =IF(H10<=0,"🔴 SIN STOCK",IF(H10<=I10,"🟠 STOCK BAJO","🟢 OK")) -> 🟢 OK
A11: ='📦 Maestro Productos'!A11 -> BAT-002 | B11: ='📦 Maestro Productos'!B11 -> Batería LiFePO4 10kWh | C11: ='📦 Maestro Productos'!C11 -> Baterías | D11: ='📦 Maestro Productos'!E11 -> Ud. | E11: 2 | F11: =SUMIF('📥 Entradas'!$B:$B,A11,'📥 Entradas'!$E:$E) -> 0 | G11: =SUMIF('📤 Salidas'!$B:$B,A11,'📤 Salidas'!$E:$E) -> 0 | H11: =E11+F11-G11 -> 2 | I11: ='📦 Maestro Productos'!H11 -> 1 | J11: ='📦 Maestro Productos'!I11 -> 5 | K11: =IF(J11=0,"N/A",TEXT(H11/J11,"0%")) -> 40% | L11: =IF(H11<=0,"🔴 SIN STOCK",IF(H11<=I11,"🟠 STOCK BAJO","🟢 OK")) -> 🟢 OK
A12: ='📦 Maestro Productos'!A12 -> AER-001 | B12: ='📦 Maestro Productos'!B12 -> Aerotermia 8kW Monobloc | C12: ='📦 Maestro Productos'!C12 -> Aerotermia | D12: ='📦 Maestro Productos'!E12 -> Ud. | E12: 6 | F12: =SUMIF('📥 Entradas'!$B:$B,A12,'📥 Entradas'!$E:$E) -> 4 | G12: =SUMIF('📤 Salidas'!$B:$B,A12,'📤 Salidas'!$E:$E) -> 1 | H12: =E12+F12-G12 -> 9 | I12: ='📦 Maestro Productos'!H12 -> 2 | J12: ='📦 Maestro Productos'!I12 -> 10 | K12: =IF(J12=0,"N/A",TEXT(H12/J12,"0%")) -> 90% | L12: =IF(H12<=0,"🔴 SIN STOCK",IF(H12<=I12,"🟠 STOCK BAJO","🟢 OK")) -> 🟢 OK
A13: ='📦 Maestro Productos'!A13 -> AER-002 | B13: ='📦 Maestro Productos'!B13 -> Aerotermia 12kW Split | C13: ='📦 Maestro Productos'!C13 -> Aerotermia | D13: ='📦 Maestro Productos'!E13 -> Ud. | E13: 3 | F13: =SUMIF('📥 Entradas'!$B:$B,A13,'📥 Entradas'!$E:$E) -> 0 | G13: =SUMIF('📤 Salidas'!$B:$B,A13,'📤 Salidas'!$E:$E) -> 0 | H13: =E13+F13-G13 -> 3 | I13: ='📦 Maestro Productos'!H13 -> 1 | J13: ='📦 Maestro Productos'!I13 -> 5 | K13: =IF(J13=0,"N/A",TEXT(H13/J13,"0%")) -> 60% | L13: =IF(H13<=0,"🔴 SIN STOCK",IF(H13<=I13,"🟠 STOCK BAJO","🟢 OK")) -> 🟢 OK
A14: ='📦 Maestro Productos'!A14 -> CAL-001 | B14: ='📦 Maestro Productos'!B14 -> Caldera Gas Condensación 24kW | C14: ='📦 Maestro Productos'!C14 -> Calefacción | D14: ='📦 Maestro Productos'!E14 -> Ud. | E14: 8 | F14: =SUMIF('📥 Entradas'!$B:$B,A14,'📥 Entradas'!$E:$E) -> 0 | G14: =SUMIF('📤 Salidas'!$B:$B,A14,'📤 Salidas'!$E:$E) -> 2 | H14: =E14+F14-G14 -> 6 | I14: ='📦 Maestro Productos'!H14 -> 3 | J14: ='📦 Maestro Productos'!I14 -> 15 | K14: =IF(J14=0,"N/A",TEXT(H14/J14,"0%")) -> 40% | L14: =IF(H14<=0,"🔴 SIN STOCK",IF(H14<=I14,"🟠 STOCK BAJO","🟢 OK")) -> 🟢 OK
A15: ='📦 Maestro Productos'!A15 -> CAL-002 | B15: ='📦 Maestro Productos'!B15 -> Radiador Aluminio 10 Elem. | C15: ='📦 Maestro Productos'!C15 -> Calefacción | D15: ='📦 Maestro Productos'!E15 -> Ud. | E15: 45 | F15: =SUMIF('📥 Entradas'!$B:$B,A15,'📥 Entradas'!$E:$E) -> 0 | G15: =SUMIF('📤 Salidas'!$B:$B,A15,'📤 Salidas'!$E:$E) -> 0 | H15: =E15+F15-G15 -> 45 | I15: ='📦 Maestro Productos'!H15 -> 20 | J15: ='📦 Maestro Productos'!I15 -> 100 | K15: =IF(J15=0,"N/A",TEXT(H15/J15,"0%")) -> 45% | L15: =IF(H15<=0,"🔴 SIN STOCK",IF(H15<=I15,"🟠 STOCK BAJO","🟢 OK")) -> 🟢 OK
... A23: ='📦 Maestro Productos'!A23 -> TUB-002 | B23: ='📦 Maestro Productos'!B23 -> Tubería Cobre 22mm (m) | C23: ='📦 Maestro Productos'!C23 -> Fontanería/Tuber. | D23: ='📦 Maestro Productos'!E23 -> m | E23: 250 | F23: =SUMIF('📥 Entradas'!$B:$B,A23,'📥 Entradas'!$E:$E) -> 0 | G23: =SUMIF('📤 Salidas'!$B:$B,A23,'📤 Salidas'!$E:$E) -> 0 | H23: =E23+F23-G23 -> 250 | I23: ='📦 Maestro Productos'!H23 -> 100 | J23: ='📦 Maestro Productos'!I23 -> 500 | K23: =IF(J23=0,"N/A",TEXT(H23/J23,"0%")) -> 50% | L23: =IF(H23<=0,"🔴 SIN STOCK",IF(H23<=I23,"🟠 STOCK BAJO","🟢 OK")) -> 🟢 OK

Sheet 📥 Entradas
A1: 📥 REGISTRO DE ENTRADAS DE MATERIAL
A2: ✏️ Registrar cada entrada: compra a proveedor, devolución de obra, ajuste de inventario, etc.
A3: Nº Mov. | B3: REF Producto | C3: Descripción | D3: Tipo Entrada | E3: Cantidad | F3: Precio Coste (€) | G3: Importe Total (€) | H3: Fecha | I3: Proveedor / Origen | J3: Nº Albarán / Factura | K3: Responsable | L3: Observaciones
A4: E-001 | B4: SOL-001 | C4: =IFERROR(VLOOKUP(B4,'📦 Maestro Productos'!$A:$B,2,0),"") -> Panel Solar Monocristalino 400W | D4: Compra Proveedor | E4: 30 | F4: 180 | G4: =E4*F4 -> 5400 | H4: 45667 | I4: Jinko Solar SL | J4: FAC-2025-0001 | K4: Carlos M. | L4: Pedido inicial temporada
A5: E-002 | B5: INV-001 | C5: =IFERROR(VLOOKUP(B5,'📦 Maestro Productos'!$A:$B,2,0),"") -> Inversor Monofásico 3kW | D5: Compra Proveedor | E5: 5 | F5: 850 | G5: =E5*F5 -> 4250 | H5: 45667 | I5: Fronius Iberia | J5: FAC-2025-0002 | K5: Carlos M.
A6: E-003 | B6: SOL-002 | C6: =IFERROR(VLOOKUP(B6,'📦 Maestro Productos'!$A:$B,2,0),"") -> Panel Solar Monocristalino 450W | D6: Compra Proveedor | E6: 20 | F6: 210 | G6: =E6*F6 -> 4200 | H6: 45672 | I6: Longi Solar | J6: FAC-2025-0003 | K6: Carlos M.
A7: E-004 | B7: AER-001 | C7: =IFERROR(VLOOKUP(B7,'📦 Maestro Productos'!$A:$B,2,0),"") -> Aerotermia 8kW Monobloc | D7: Compra Proveedor | E7: 4 | F7: 1900 | G7: =E7*F7 -> 7600 | H7: 45677 | I7: Mitsubishi ES | J7: FAC-2025-0004 | K7: Ana L. | L7: Campaña invierno
A8: E-005 | B8: CAB-001 | C8: =IFERROR(VLOOKUP(B8,'📦 Maestro Productos'!$A:$B,2,0),"") -> Cable Solar 4mm² (m) | D8: Compra Proveedor | E8: 500 | F8: 0.85 | G8: =E8*F8 -> 425 | H8: 45679 | I8: Prysmian Group | J8: FAC-2025-0005 | K8: Carlos M.
A9: E-006 | B9: BAT-001 | C9: =IFERROR(VLOOKUP(B9,'📦 Maestro Productos'!$A:$B,2,0),"") -> Batería LiFePO4 5kWh | D9: Devolución Obra | E9: 2 | F9: 2200 | G9: =E9*F9 -> 4400 | H9: 45691 | I9: Obra Ref. 2024-087 | J9: N/A | K9: Ana L. | L9: Cambio especificaciones
C10: =IFERROR(VLOOKUP(B10,'📦 Maestro Productos'!$A:$B,2,0),"") | G10: =IF(E10="","",E10*F10)
C11: =IFERROR(VLOOKUP(B11,'📦 Maestro Productos'!$A:$B,2,0),"") | G11: =IF(E11="","",E11*F11)
C12: =IFERROR(VLOOKUP(B12,'📦 Maestro Productos'!$A:$B,2,0),"") | G12: =IF(E12="","",E12*F12)
C13: =IFERROR(VLOOKUP(B13,'📦 Maestro Productos'!$A:$B,2,0),"") | G13: =IF(E13="","",E13*F13)
C14: =IFERROR(VLOOKUP(B14,'📦 Maestro Productos'!$A:$B,2,0),"") | G14: =IF(E14="","",E14*F14)
C15: =IFERROR(VLOOKUP(B15,'📦 Maestro Productos'!$A:$B,2,0),"") | G15: =IF(E15="","",E15*F15)
C16: =IFERROR(VLOOKUP(B16,'📦 Maestro Productos'!$A:$B,2,0),"") | G16: =IF(E16="","",E16*F16)
C17: =IFERROR(VLOOKUP(B17,'📦 Maestro Productos'!$A:$B,2,0),"") | G17: =IF(E17="","",E17*F17)
C18: =IFERROR(VLOOKUP(B18,'📦 Maestro Productos'!$A:$B,2,0),"") | G18: =IF(E18="","",E18*F18)
C19: =IFERROR(VLOOKUP(B19,'📦 Maestro Productos'!$A:$B,2,0),"") | G19: =IF(E19="","",E19*F19)
C20: =IFERROR(VLOOKUP(B20,'📦 Maestro Productos'!$A:$B,2,0),"") | G20: =IF(E20="","",E20*F20)
C21: =IFERROR(VLOOKUP(B21,'📦 Maestro Productos'!$A:$B,2,0),"") | G21: =IF(E21="","",E21*F21)
... C199: =IFERROR(VLOOKUP(B199,'📦 Maestro Productos'!$A:$B,2,0),"") | G199: =IF(E199="","",E199*F199)

Sheet 📤 Salidas
A1: 📤 REGISTRO DE SALIDAS DE MATERIAL
A2: ✏️ Registrar cada salida: material a obra, venta directa, merma, etc. El REF debe coincidir exactamente.
A3: Nº Mov. | B3: REF Producto | C3: Descripción | D3: Tipo Salida | E3: Cantidad | F3: Precio Venta (€) | G3: Importe Total (€) | H3: Fecha | I3: Destino / Obra / Cliente | J3: Nº Pedido / Factura | K3: Responsable | L3: Observaciones
A4: S-001 | B4: SOL-001 | C4: =IFERROR(VLOOKUP(B4,'📦 Maestro Productos'!$A:$B,2,0),"") -> Panel Solar Monocristalino 400W | D4: Obra Instalación | E4: 10 | F4: 295 | G4: =E4*F4 -> 2950 | H4: 45675 | I4: Obra CL-2025-001 Getafe | J4: PED-001 | K4: Luis G. | L4: Inst. fotovoltaica chalet
A5: S-002 | B5: INV-001 | C5: =IFERROR(VLOOKUP(B5,'📦 Maestro Productos'!$A:$B,2,0),"") -> Inversor Monofásico 3kW | D5: Obra Instalación | E5: 2 | F5: 1350 | G5: =E5*F5 -> 2700 | H5: 45675 | I5: Obra CL-2025-001 Getafe | J5: PED-001 | K5: Luis G.
A6: S-003 | B6: EST-001 | C6: =IFERROR(VLOOKUP(B6,'📦 Maestro Productos'!$A:$B,2,0),"") -> Estructura Tejado Inclinado (kit) | D6: Obra Instalación | E6: 10 | F6: 210 | G6: =E6*F6 -> 2100 | H6: 45675 | I6: Obra CL-2025-001 Getafe | J6: PED-001 | K6: Luis G.
A7: S-004 | B7: AER-001 | C7: =IFERROR(VLOOKUP(B7,'📦 Maestro Productos'!$A:$B,2,0),"") -> Aerotermia 8kW Monobloc | D7: Obra Instalación | E7: 1 | F7: 3200 | G7: =E7*F7 -> 3200 | H7: 45682 | I7: Obra CL-2025-002 Alcorcón | J7: PED-002 | K7: María S. | L7: Aerotermia residencial
A8: S-005 | B8: CAL-001 | C8: =IFERROR(VLOOKUP(B8,'📦 Maestro Productos'!$A:$B,2,0),"") -> Caldera Gas Condensación 24kW | D8: Obra Instalación | E8: 2 | F8: 1250 | G8: =E8*F8 -> 2500 | H8: 45685 | I8: Obra CL-2025-003 Leganés | J8: PED-003 | K8: Luis G.
A9: S-006 | B9: SOL-002 | C9: =IFERROR(VLOOKUP(B9,'📦 Maestro Productos'!$A:$B,2,0),"") -> Panel Solar Monocristalino 450W | D9: Obra Instalación | E9: 15 | F9: 340 | G9: =E9*F9 -> 5100 | H9: 45693 | I9: Obra CL-2025-004 Majadahonda | J9: PED-004 | K9: María S. | L9: 20 paneles proyecto grande
A10: S-007 | B10: INV-002 | C10: =IFERROR(VLOOKUP(B10,'📦 Maestro Productos'!$A:$B,2,0),"") -> Inversor Monofásico 5kW | D10: Venta Directa | E10: 1 | F10: 1580 | G10: =E10*F10 -> 1580 | H10: 45696 | I10: Cliente Particular - J.Ruiz | J10: PED-005 | K10: Carlos M. | L10: Venta sin instalación
A11: S-008 | B11: CAB-001 | C11: =IFERROR(VLOOKUP(B11,'📦 Maestro Productos'!$A:$B,2,0),"") -> Cable Solar 4mm² (m) | D11: Obra Instalación | E11: 250 | F11: 1.6 | G11: =E11*F11 -> 400 | H11: 45698 | I11: Obra CL-2025-004 Majadahonda | J11: PED-004 | K11: Luis G.
C12: =IFERROR(VLOOKUP(B12,'📦 Maestro Productos'!$A:$B,2,0),"") | G12: =IF(E12="","",E12*F12)
C13: =IFERROR(VLOOKUP(B13,'📦 Maestro Productos'!$A:$B,2,0),"") | G13: =IF(E13="","",E13*F13)
C14: =IFERROR(VLOOKUP(B14,'📦 Maestro Productos'!$A:$B,2,0),"") | G14: =IF(E14="","",E14*F14)
C15: =IFERROR(VLOOKUP(B15,'📦 Maestro Productos'!$A:$B,2,0),"") | G15: =IF(E15="","",E15*F15)
C16: =IFERROR(VLOOKUP(B16,'📦 Maestro Productos'!$A:$B,2,0),"") | G16: =IF(E16="","",E16*F16)
C17: =IFERROR(VLOOKUP(B17,'📦 Maestro Productos'!$A:$B,2,0),"") | G17: =IF(E17="","",E17*F17)
C18: =IFERROR(VLOOKUP(B18,'📦 Maestro Productos'!$A:$B,2,0),"") | G18: =IF(E18="","",E18*F18)
C19: =IFERROR(VLOOKUP(B19,'📦 Maestro Productos'!$A:$B,2,0),"") | G19: =IF(E19="","",E19*F19)
C20: =IFERROR(VLOOKUP(B20,'📦 Maestro Productos'!$A:$B,2,0),"") | G20: =IF(E20="","",E20*F20)
C21: =IFERROR(VLOOKUP(B21,'📦 Maestro Productos'!$A:$B,2,0),"") | G21: =IF(E21="","",E21*F21)
C22: =IFERROR(VLOOKUP(B22,'📦 Maestro Productos'!$A:$B,2,0),"") | G22: =IF(E22="","",E22*F22)
C23: =IFERROR(VLOOKUP(B23,'📦 Maestro Productos'!$A:$B,2,0),"") | G23: =IF(E23="","",E23*F23)
... C499: =IFERROR(VLOOKUP(B499,'📦 Maestro Productos'!$A:$B,2,0),"") | G499: =IF(E499="","",E499*F499)

Sheet 📦 Maestro Productos
A1: 🏭 MAESTRO DE PRODUCTOS — Control de Inventario
A2: ⚠️ NO modificar los códigos de referencia — son la clave de todo el sistema
A3: REF | B3: Descripción del Producto | C3: Categoría | D3: Marca/Fabricante | E3: Unidad | F3: Precio Coste (€) | G3: Precio Venta (€) | H3: Stock Mínimo | I3: Stock Máximo | J3: Ubicación Almacén
A4: SOL-001 | B4: Panel Solar Monocristalino 400W | C4: Placas Solares | D4: Jinko Solar | E4: Ud. | F4: 180 | G4: 295 | H4: 10 | I4: 100 | J4: Nave A - Estante 1
A5: SOL-002 | B5: Panel Solar Monocristalino 450W | C5: Placas Solares | D5: Longi Solar | E5: Ud. | F5: 210 | G5: 340 | H5: 10 | I5: 80 | J5: Nave A - Estante 1
A6: SOL-003 | B6: Panel Solar Bifacial 500W | C6: Placas Solares | D6: Trina Solar | E6: Ud. | F6: 250 | G6: 399 | H6: 5 | I6: 50 | J6: Nave A - Estante 2
A7: INV-001 | B7: Inversor Monofásico 3kW | C7: Inversores | D7: Fronius | E7: Ud. | F7: 850 | G7: 1350 | H7: 3 | I7: 20 | J7: Nave B - Estante 1
A8: INV-002 | B8: Inversor Monofásico 5kW | C8: Inversores | D8: Fronius | E8: Ud. | F8: 980 | G8: 1580 | H8: 3 | I8: 20 | J8: Nave B - Estante 1
A9: INV-003 | B9: Inversor Trifásico 10kW | C9: Inversores | D9: SMA | E9: Ud. | F9: 1800 | G9: 2900 | H9: 2 | I9: 10 | J9: Nave B - Estante 2
A10: BAT-001 | B10: Batería LiFePO4 5kWh | C10: Baterías | D10: BYD | E10: Ud. | F10: 2200 | G10: 3500 | H10: 2 | I10: 10 | J10: Nave B - Estante 3
A11: BAT-002 | B11: Batería LiFePO4 10kWh | C11: Baterías | D11: BYD | E11: Ud. | F11: 4100 | G11: 6500 | H11: 1 | I11: 5 | J11: Nave B - Estante 3
A12: AER-001 | B12: Aerotermia 8kW Monobloc | C12: Aerotermia | D12: Mitsubishi | E12: Ud. | F12: 1900 | G12: 3200 | H12: 2 | I12: 10 | J12: Nave C - Estante 1
A13: AER-002 | B13: Aerotermia 12kW Split | C13: Aerotermia | D13: Daikin | E13: Ud. | F13: 2800 | G13: 4500 | H13: 1 | I13: 5 | J13: Nave C - Estante 1
A14: CAL-001 | B14: Caldera Gas Condensación 24kW | C14: Calefacción | D14: Vaillant | E14: Ud. | F14: 750 | G14: 1250 | H14: 3 | I14: 15 | J14: Nave C - Estante 2
A15: CAL-002 | B15: Radiador Aluminio 10 Elem. | C15: Calefacción | D15: General | E15: Ud. | F15: 85 | G15: 145 | H15: 20 | I15: 100 | J15: Nave C - Estante 3
... A23: TUB-002 | B23: Tubería Cobre 22mm (m) | C23: Fontanería/Tuber. | D23: Roca | E23: m | F23: 8.5 | G23: 16 | H23: 100 | I23: 500 | J23: Nave D - Estante 2

Sheet 📋 Proyectos
A1: 📋 MAESTRO DE PROYECTOS — Control completo por obra
A2: Registra aquí cada proyecto. Los costes reales se calculan automáticamente desde las hojas de Salidas y Horas.
A3: ⚙️ Tarifa hora MO (€/h): | E3: 35 | F3: ← Cambiar aquí la tarifa de mano de obra para recalcular todo
A4: IDENTIFICACIÓN | G4: CONTROL DE TIEMPO | M4: CONTROL DE MATERIAL | Q4: MANO DE OBRA | U4: RESULTADO FINANCIERO | Y4: CALIDAD
A5: Nº Proyecto | B5: Cliente | C5: Localidad | D5: Tipo Instalación | E5: Equipo Asignado | F5: Estado | G5: Fecha Inicio | H5: Fecha Fin Estimada | I5: Fecha Fin Real | J5: Días Estimados | K5: Días Reales | L5: Desv. Días | M5: Ppto. Material Estimado (€) | N5: Coste Material Real (€) | O5: Desv. Material (€) | P5: % Desv. Material | Q5: Horas MO Estimadas | R5: Horas MO Reales | S5: Coste MO Estimado (€) | T5: Coste MO Real (€) | U5: Precio Venta Total (€) | V5: Coste Total Real (€) | W5: Margen Bruto (€) | X5: % Margen | Y5: Nº Incidencias | Z5: Rentab. Semáforo
A6: PRY-001 | B6: Familia Rodríguez | C6: Getafe (Madrid) | D6: Solar Residencial | E6: Equipo Alpha | F6: Completado | G6: 45665 | H6: 45679 | I6: 45678 | J6: =IF(H6="","",H6-G6) -> 14 | K6: =IF(I6="","",I6-G6) -> 13 | L6: =IF(OR(J6="",K6=""),"",K6-J6) -> -1 | M6: -1 | N6: =IFERROR(SUMIF('📤 Salidas'!$I:$I,"*"&A6&"*",'📤 Salidas'!$G:$G),0) -> 0 | O6: =IF(M6=0,"",N6-M6) -> 1 | P6: =IF(M6=0,"",N6/M6-1) -> -1 | R6: =IFERROR(SUMIF('⏱️ Horas MO'!$B:$B,A6,'⏱️ Horas MO'!$G:$G),0) -> 38 | S6: =IF(Q6=0,"",Q6*$E$3) | T6: =IF(R6=0,"",R6*$E$3) -> 1330 | V6: =IF(N6=0,"",N6+T6) | W6: =IF(V6="","",U6-V6) | X6: =IF(OR(W6="",U6=0),"",W6/U6) | Y6: =IFERROR(COUNTIF('⚠️ Incidencias'!$B:$B,A6),0) -> 1 | Z6: =IF(X6="","⚪",IF(X6>=0.3,"🟢",IF(X6>=0.15,"🟡","🔴"))) -> ⚪
A7: PRY-002 | B7: Comunidad Sta. Ana | C7: Alcorcón (Madrid) | D7: Solar Industrial | E7: Equipo Beta | F7: Completado | G7: 45672 | H7: 45693 | I7: 45696 | J7: =IF(H7="","",H7-G7) -> 21 | K7: =IF(I7="","",I7-G7) -> 24 | L7: =IF(OR(J7="",K7=""),"",K7-J7) -> 3 | M7: 3 | N7: =IFERROR(SUMIF('📤 Salidas'!$I:$I,"*"&A7&"*",'📤 Salidas'!$G:$G),0) -> 0 | O7: =IF(M7=0,"",N7-M7) -> -3 | P7: =IF(M7=0,"",N7/M7-1) -> -1 | R7: =IFERROR(SUMIF('⏱️ Horas MO'!$B:$B,A7,'⏱️ Horas MO'!$G:$G),0) -> 16 | S7: =IF(Q7=0,"",Q7*$E$3) | T7: =IF(R7=0,"",R7*$E$3) -> 560 | V7: =IF(N7=0,"",N7+T7) | W7: =IF(V7="","",U7-V7) | X7: =IF(OR(W7="",U7=0),"",W7/U7) | Y7: =IFERROR(COUNTIF('⚠️ Incidencias'!$B:$B,A7),0) -> 2 | Z7: =IF(X7="","⚪",IF(X7>=0.3,"🟢",IF(X7>=0.15,"🟡","🔴"))) -> ⚪
A8: PRY-003 | B8: José M. Herrera | C8: Leganés (Madrid) | D8: Aerotermia | E8: Equipo Alpha | F8: Completado | G8: 45677 | H8: 45684 | I8: 45683 | J8: =IF(H8="","",H8-G8) -> 7 | K8: =IF(I8="","",I8-G8) -> 6 | L8: =IF(OR(J8="",K8=""),"",K8-J8) -> -1 | M8: -1 | N8: =IFERROR(SUMIF('📤 Salidas'!$I:$I,"*"&A8&"*",'📤 Salidas'!$G:$G),0) -> 0 | O8: =IF(M8=0,"",N8-M8) -> 1 | P8: =IF(M8=0,"",N8/M8-1) -> -1 | R8: =IFERROR(SUMIF('⏱️ Horas MO'!$B:$B,A8,'⏱️ Horas MO'!$G:$G),0) -> 22 | S8: =IF(Q8=0,"",Q8*$E$3) | T8: =IF(R8=0,"",R8*$E$3) -> 770 | V8: =IF(N8=0,"",N8+T8) | W8: =IF(V8="","",U8-V8) | X8: =IF(OR(W8="",U8=0),"",W8/U8) | Y8: =IFERROR(COUNTIF('⚠️ Incidencias'!$B:$B,A8),0) -> 0 | Z8: =IF(X8="","⚪",IF(X8>=0.3,"🟢",IF(X8>=0.15,"🟡","🔴"))) -> ⚪
A9: PRY-004 | B9: Nave Industrial López | C9: Majadahonda (Madrid) | D9: Solar Industrial | E9: Equipo Gamma | F9: En Ejecución | G9: 45691 | H9: 45717 | J9: =IF(H9="","",H9-G9) -> 26 | K9: =IF(I9="","",I9-G9) | L9: =IF(OR(J9="",K9=""),"",K9-J9) | N9: =IFERROR(SUMIF('📤 Salidas'!$I:$I,"*"&A9&"*",'📤 Salidas'!$G:$G),0) -> 0 | O9: =IF(M9=0,"",N9-M9) | P9: =IF(M9=0,"",N9/M9-1) | R9: =IFERROR(SUMIF('⏱️ Horas MO'!$B:$B,A9,'⏱️ Horas MO'!$G:$G),0) -> 16 | S9: =IF(Q9=0,"",Q9*$E$3) | T9: =IF(R9=0,"",R9*$E$3) -> 560 | V9: =IF(N9=0,"",N9+T9) | W9: =IF(V9="","",U9-V9) | X9: =IF(OR(W9="",U9=0),"",W9/U9) | Y9: =IFERROR(COUNTIF('⚠️ Incidencias'!$B:$B,A9),0) -> 1 | Z9: =IF(X9="","⚪",IF(X9>=0.3,"🟢",IF(X9>=0.15,"🟡","🔴"))) -> ⚪
A10: PRY-005 | B10: Hotel Mediterráneo | C10: Fuenlabrada (Madrid) | D10: Mixto Solar+Aero | E10: Equipo Beta | F10: En Ejecución | G10: 45698 | H10: 45731 | J10: =IF(H10="","",H10-G10) -> 33 | K10: =IF(I10="","",I10-G10) | L10: =IF(OR(J10="",K10=""),"",K10-J10) | N10: =IFERROR(SUMIF('📤 Salidas'!$I:$I,"*"&A10&"*",'📤 Salidas'!$G:$G),0) -> 0 | O10: =IF(M10=0,"",N10-M10) | P10: =IF(M10=0,"",N10/M10-1) | R10: =IFERROR(SUMIF('⏱️ Horas MO'!$B:$B,A10,'⏱️ Horas MO'!$G:$G),0) -> 8 | S10: =IF(Q10=0,"",Q10*$E$3) | T10: =IF(R10=0,"",R10*$E$3) -> 280 | V10: =IF(N10=0,"",N10+T10) | W10: =IF(V10="","",U10-V10) | X10: =IF(OR(W10="",U10=0),"",W10/U10) | Y10: =IFERROR(COUNTIF('⚠️ Incidencias'!$B:$B,A10),0) -> 1 | Z10: =IF(X10="","⚪",IF(X10>=0.3,"🟢",IF(X10>=0.15,"🟡","🔴"))) -> ⚪
A11: PRY-006 | B11: Clínica Dental Pérez | C11: Móstoles (Madrid) | D11: Calefacción | E11: Equipo Delta | F11: Completado | G11: 45662 | H11: 45669 | I11: 45671 | J11: =IF(H11="","",H11-G11) -> 7 | K11: =IF(I11="","",I11-G11) -> 9 | L11: =IF(OR(J11="",K11=""),"",K11-J11) -> 2 | M11: 2 | N11: =IFERROR(SUMIF('📤 Salidas'!$I:$I,"*"&A11&"*",'📤 Salidas'!$G:$G),0) -> 0 | O11: =IF(M11=0,"",N11-M11) -> -2 | P11: =IF(M11=0,"",N11/M11-1) -> -1 | R11: =IFERROR(SUMIF('⏱️ Horas MO'!$B:$B,A11,'⏱️ Horas MO'!$G:$G),0) -> 30 | S11: =IF(Q11=0,"",Q11*$E$3) | T11: =IF(R11=0,"",R11*$E$3) -> 1050 | V11: =IF(N11=0,"",N11+T11) | W11: =IF(V11="","",U11-V11) | X11: =IF(OR(W11="",U11=0),"",W11/U11) | Y11: =IFERROR(COUNTIF('⚠️ Incidencias'!$B:$B,A11),0) -> 1 | Z11: =IF(X11="","⚪",IF(X11>=0.3,"🟢",IF(X11>=0.15,"🟡","🔴"))) -> ⚪
A12: PRY-007 | B12: Polideportivo Municipal | C12: Pozuelo (Madrid) | D12: Solar Industrial | E12: Equipo Alpha | F12: Completado | G12: 45685 | H12: 45706 | I12: 45705 | J12: =IF(H12="","",H12-G12) -> 21 | K12: =IF(I12="","",I12-G12) -> 20 | L12: =IF(OR(J12="",K12=""),"",K12-J12) -> -1 | M12: -1 | N12: =IFERROR(SUMIF('📤 Salidas'!$I:$I,"*"&A12&"*",'📤 Salidas'!$G:$G),0) -> 0 | O12: =IF(M12=0,"",N12-M12) -> 1 | P12: =IF(M12=0,"",N12/M12-1) -> -1 | R12: =IFERROR(SUMIF('⏱️ Horas MO'!$B:$B,A12,'⏱️ Horas MO'!$G:$G),0) -> 40 | S12: =IF(Q12=0,"",Q12*$E$3) | T12: =IF(R12=0,"",R12*$E$3) -> 1400 | V12: =IF(N12=0,"",N12+T12) | W12: =IF(V12="","",U12-V12) | X12: =IF(OR(W12="",U12=0),"",W12/U12) | Y12: =IFERROR(COUNTIF('⚠️ Incidencias'!$B:$B,A12),0) -> 0 | Z12: =IF(X12="","⚪",IF(X12>=0.3,"🟢",IF(X12>=0.15,"🟡","🔴"))) -> ⚪
A13: PRY-008 | B13: Residencia 3ª Edad | C13: Alcalá de Henares | D13: Aerotermia | E13: Equipo Gamma | F13: Completado | G13: 45689 | H13: 45698 | I13: 45700 | J13: =IF(H13="","",H13-G13) -> 9 | K13: =IF(I13="","",I13-G13) -> 11 | L13: =IF(OR(J13="",K13=""),"",K13-J13) -> 2 | M13: 2 | N13: =IFERROR(SUMIF('📤 Salidas'!$I:$I,"*"&A13&"*",'📤 Salidas'!$G:$G),0) -> 0 | O13: =IF(M13=0,"",N13-M13) -> -2 | P13: =IF(M13=0,"",N13/M13-1) -> -1 | R13: =IFERROR(SUMIF('⏱️ Horas MO'!$B:$B,A13,'⏱️ Horas MO'!$G:$G),0) -> 16 | S13: =IF(Q13=0,"",Q13*$E$3) | T13: =IF(R13=0,"",R13*$E$3) -> 560 | V13: =IF(N13=0,"",N13+T13) | W13: =IF(V13="","",U13-V13) | X13: =IF(OR(W13="",U13=0),"",W13/U13) | Y13: =IFERROR(COUNTIF('⚠️ Incidencias'!$B:$B,A13),0) -> 1 | Z13: =IF(X13="","⚪",IF(X13>=0.3,"🟢",IF(X13>=0.15,"🟡","🔴"))) -> ⚪
A14: PRY-009 | B14: Chalet García-Vega | C14: Boadilla del Monte | D14: Solar Residencial | E14: Equipo Delta | F14: En Presupuesto | L14: =IF(OR(J14="",K14=""),"",K14-J14) | N14: =IFERROR(SUMIF('📤 Salidas'!$I:$I,"*"&A14&"*",'📤 Salidas'!$G:$G),0) -> 0 | O14: =IF(M14=0,"",N14-M14) | P14: =IF(M14=0,"",N14/M14-1) | R14: =IFERROR(SUMIF('⏱️ Horas MO'!$B:$B,A14,'⏱️ Horas MO'!$G:$G),0) -> 0 | S14: =IF(Q14=0,"",Q14*$E$3) | T14: =IF(R14=0,"",R14*$E$3) | V14: =IF(N14=0,"",N14+T14) | W14: =IF(V14="","",U14-V14) | X14: =IF(OR(W14="",U14=0),"",W14/U14) | Y14: =IFERROR(COUNTIF('⚠️ Incidencias'!$B:$B,A14),0) -> 0 | Z14: =IF(X14="","⚪",IF(X14>=0.3,"🟢",IF(X14>=0.15,"🟡","🔴"))) -> ⚪
A15: PRY-010 | B15: Fábrica Textil Norte | C15: Torrejón de Ardoz | D15: Solar Industrial | E15: Equipo Beta | F15: En Presupuesto | L15: =IF(OR(J15="",K15=""),"",K15-J15) | N15: =IFERROR(SUMIF('📤 Salidas'!$I:$I,"*"&A15&"*",'📤 Salidas'!$G:$G),0) -> 0 | O15: =IF(M15=0,"",N15-M15) | P15: =IF(M15=0,"",N15/M15-1) | R15: =IFERROR(SUMIF('⏱️ Horas MO'!$B:$B,A15,'⏱️ Horas MO'!$G:$G),0) -> 0 | S15: =IF(Q15=0,"",Q15*$E$3) | T15: =IF(R15=0,"",R15*$E$3) | V15: =IF(N15=0,"",N15+T15) | W15: =IF(V15="","",U15-V15) | X15: =IF(OR(W15="",U15=0),"",W15/U15) | Y15: =IFERROR(COUNTIF('⚠️ Incidencias'!$B:$B,A15),0) -> 0 | Z15: =IF(X15="","⚪",IF(X15>=0.3,"🟢",IF(X15>=0.15,"🟡","🔴"))) -> ⚪

Sheet ⏱️ Horas MO
A1: ⏱️ HORAS & MANO DE OBRA — Registro por técnico y proyecto
A2: Cada fila = una jornada o actividad. El coste se calcula automáticamente con la tarifa definida en Proyectos (E3).
A3: Nº Mov. | B3: Nº Proyecto | C3: Equipo | D3: Técnico | E3: Fecha | F3: Concepto | G3: Horas | H3: Tarifa €/h | I3: Importe (€) | J3: Observaciones
A4: H-001 | B4: PRY-001 | C4: Equipo Alpha | D4: Luis García | E4: 45665 | F4: Instalación paneles | G4: 8 | H4: ='📋 Proyectos'!$E$3 -> 35 | I4: =G4*H4 -> 280
A5: H-002 | B5: PRY-001 | C5: Equipo Alpha | D5: Pedro Ruiz | E5: 45665 | F5: Instalación paneles | G5: 8 | H5: ='📋 Proyectos'!$E$3 -> 35 | I5: =G5*H5 -> 280
A6: H-003 | B6: PRY-001 | C6: Equipo Alpha | D6: Luis García | E6: 45666 | F6: Cableado y conexiones | G6: 8 | H6: ='📋 Proyectos'!$E$3 -> 35 | I6: =G6*H6 -> 280
A7: H-004 | B7: PRY-001 | C7: Equipo Alpha | D7: Pedro Ruiz | E7: 45666 | F7: Cableado y conexiones | G7: 7 | H7: ='📋 Proyectos'!$E$3 -> 35 | I7: =G7*H7 -> 245
A8: H-005 | B8: PRY-001 | C8: Equipo Alpha | D8: Luis García | E8: 45678 | F8: Puesta en marcha | G8: 7 | H8: ='📋 Proyectos'!$E$3 -> 35 | I8: =G8*H8 -> 245
A9: H-006 | B9: PRY-003 | C9: Equipo Alpha | D9: Luis García | E9: 45677 | F9: Instalación aerotermia | G9: 8 | H9: ='📋 Proyectos'!$E$3 -> 35 | I9: =G9*H9 -> 280
A10: H-007 | B10: PRY-003 | C10: Equipo Alpha | D10: Pedro Ruiz | E10: 45677 | F10: Fontanería y conexiones | G10: 7 | H10: ='📋 Proyectos'!$E$3 -> 35 | I10: =G10*H10 -> 245
A11: H-008 | B11: PRY-003 | C11: Equipo Alpha | D11: Luis García | E11: 45683 | F11: Puesta en marcha | G11: 7 | H11: ='📋 Proyectos'!$E$3 -> 35 | I11: =G11*H11 -> 245
A12: H-009 | B12: PRY-006 | C12: Equipo Delta | D12: Javier Martín | E12: 45662 | F12: Instalación calefacción | G12: 8 | H12: ='📋 Proyectos'!$E$3 -> 35 | I12: =G12*H12 -> 280
A13: H-010 | B13: PRY-006 | C13: Equipo Delta | D13: Elena Torres | E13: 45662 | F13: Instalación calefacción | G13: 8 | H13: ='📋 Proyectos'!$E$3 -> 35 | I13: =G13*H13 -> 280
A14: H-011 | B14: PRY-006 | C14: Equipo Delta | D14: Javier Martín | E14: 45671 | F14: Ajuste y puesta en marcha | G14: 8 | H14: ='📋 Proyectos'!$E$3 -> 35 | I14: =G14*H14 -> 280 | J14: Revisita por mal ajuste
A15: H-012 | B15: PRY-006 | C15: Equipo Delta | D15: Elena Torres | E15: 45671 | F15: Ajuste y puesta en marcha | G15: 6 | H15: ='📋 Proyectos'!$E$3 -> 35 | I15: =G15*H15 -> 210
A16: H-013 | B16: PRY-007 | C16: Equipo Alpha | D16: Luis García | E16: 45685 | F16: Instalación estructura | G16: 8 | H16: ='📋 Proyectos'!$E$3 -> 35 | I16: =G16*H16 -> 280
A17: H-014 | B17: PRY-007 | C17: Equipo Alpha | D17: Pedro Ruiz | E17: 45685 | F17: Instalación estructura | G17: 8 | H17: ='📋 Proyectos'!$E$3 -> 35 | I17: =G17*H17 -> 280
A18: H-015 | B18: PRY-007 | C18: Equipo Alpha | D18: Ana López | E18: 45691 | F18: Paneles y cableado | G18: 8 | H18: ='📋 Proyectos'!$E$3 -> 35 | I18: =G18*H18 -> 280
A19: H-016 | B19: PRY-007 | C19: Equipo Alpha | D19: Luis García | E19: 45705 | F19: Puesta en marcha | G19: 8 | H19: ='📋 Proyectos'!$E$3 -> 35 | I19: =G19*H19 -> 280
A20: H-017 | B20: PRY-007 | C20: Equipo Alpha | D20: Pedro Ruiz | E20: 45705 | F20: Puesta en marcha | G20: 8 | H20: ='📋 Proyectos'!$E$3 -> 35 | I20: =G20*H20 -> 280
A21: H-018 | B21: PRY-008 | C21: Equipo Gamma | D21: María Sánchez | E21: 45689 | F21: Instalación aerotermia | G21: 8 | H21: ='📋 Proyectos'!$E$3 -> 35 | I21: =G21*H21 -> 280
A22: H-019 | B22: PRY-008 | C22: Equipo Gamma | D22: María Sánchez | E22: 45700 | F22: Puesta en marcha + ajuste | G22: 8 | H22: ='📋 Proyectos'!$E$3 -> 35 | I22: =G22*H22 -> 280 | J22: Incidencia presión
A23: H-020 | B23: PRY-002 | C23: Equipo Beta | D23: Ana López | E23: 45672 | F23: Instalación paneles | G23: 8 | H23: ='📋 Proyectos'!$E$3 -> 35 | I23: =G23*H23 -> 280
A24: H-021 | B24: PRY-002 | C24: Equipo Beta | D24: Ana López | E24: 45696 | F24: Puesta en marcha | G24: 8 | H24: ='📋 Proyectos'!$E$3 -> 35 | I24: =G24*H24 -> 280 | J24: Retraso por lluvia
A25: H-022 | B25: PRY-004 | C25: Equipo Gamma | D25: María Sánchez | E25: 45691 | F25: Instalación industrial | G25: 8 | H25: ='📋 Proyectos'!$E$3 -> 35 | I25: =G25*H25 -> 280
A26: H-023 | B26: PRY-004 | C26: Equipo Gamma | D26: María Sánchez | E26: 45698 | F26: Cableado industrial | G26: 8 | H26: ='📋 Proyectos'!$E$3 -> 35 | I26: =G26*H26 -> 280
A27: H-024 | B27: PRY-005 | C27: Equipo Beta | D27: Ana López | E27: 45698 | F27: Inicio instalación | G27: 8 | H27: ='📋 Proyectos'!$E$3 -> 35 | I27: =G27*H27 -> 280
H28: ='📋 Proyectos'!$E$3 -> 35 | I28: =IF(G28="","",G28*H28)
H29: ='📋 Proyectos'!$E$3 -> 35 | I29: =IF(G29="","",G29*H29)
H30: ='📋 Proyectos'!$E$3 -> 35 | I30: =IF(G30="","",G30*H30)
H31: ='📋 Proyectos'!$E$3 -> 35 | I31: =IF(G31="","",G31*H31)
H32: ='📋 Proyectos'!$E$3 -> 35 | I32: =IF(G32="","",G32*H32)
H33: ='📋 Proyectos'!$E$3 -> 35 | I33: =IF(G33="","",G33*H33)
H34: ='📋 Proyectos'!$E$3 -> 35 | I34: =IF(G34="","",G34*H34)
H35: ='📋 Proyectos'!$E$3 -> 35 | I35: =IF(G35="","",G35*H35)
H36: ='📋 Proyectos'!$E$3 -> 35 | I36: =IF(G36="","",G36*H36)
H37: ='📋 Proyectos'!$E$3 -> 35 | I37: =IF(G37="","",G37*H37)
H38: ='📋 Proyectos'!$E$3 -> 35 | I38: =IF(G38="","",G38*H38)
H39: ='📋 Proyectos'!$E$3 -> 35 | I39: =IF(G39="","",G39*H39)
... H299: ='📋 Proyectos'!$E$3 -> 35 | I299: =IF(G299="","",G299*H299)

Sheet ⚠️ Incidencias
A1: ⚠️ REGISTRO DE INCIDENCIAS — Revisitas, averías y reclamaciones
A2: Registrar TODA incidencia post-instalación. Es la clave para detectar qué equipos o materiales dan más problemas.
A3: Nº Inc. | B3: Nº Proyecto | C3: Equipo | D3: Técnico Responsable | E3: Fecha Inc. | F3: Tipo | G3: Descripción | H3: Horas Extra | I3: Coste Mat. Extra (€) | J3: Coste Total Inc. (€) | K3: Estado | L3: Fecha Cierre
A4: INC-001 | B4: PRY-002 | C4: Equipo Beta | D4: Ana López | E4: 45696 | F4: Revisita | G4: Inversor no conecta con la red — configuración errónea | H4: 3 | I4: 0 | J4: =H4*'📋 Proyectos'!$E$3+I4 -> 105 | K4: Cerrada | L4: 45696
A5: INC-002 | B5: PRY-006 | C5: Equipo Delta | D5: Javier Martín | E5: 45671 | F5: Ajuste Técnico | G5: Presión calefacción mal calibrada — revisita necesaria | H5: 4 | I5: 45 | J5: =H5*'📋 Proyectos'!$E$3+I5 -> 185 | K5: Cerrada | L5: 45671
A6: INC-003 | B6: PRY-008 | C6: Equipo Gamma | D6: María Sánchez | E6: 45700 | F6: Avería Equipo | G6: Compresor aerotermia con ruido anómalo — revisión | H6: 5 | I6: 0 | J6: =H6*'📋 Proyectos'!$E$3+I6 -> 175 | K6: Cerrada | L6: 45702
A7: INC-004 | B7: PRY-001 | C7: Equipo Alpha | D7: Luis García | E7: 45690 | F7: Reclamación Cliente | G7: Cliente reporta que app monitorización no funciona | H7: 2 | I7: 0 | J7: =H7*'📋 Proyectos'!$E$3+I7 -> 70 | K7: Cerrada | L7: 45691
A8: INC-005 | B8: PRY-002 | C8: Equipo Beta | D8: Ana López | E8: 45703 | F8: Fallo Material | G8: Microinversor defectuoso — sustitución en garantía | H8: 3 | I8: 180 | J8: =H8*'📋 Proyectos'!$E$3+I8 -> 285 | K8: Cerrada | L8: 45704
A9: INC-006 | B9: PRY-004 | C9: Equipo Gamma | D9: María Sánchez | E9: 45706 | F9: Ajuste Técnico | G9: Estructura no nivelada correctamente — corrección | H9: 4 | I9: 0 | J9: =H9*'📋 Proyectos'!$E$3+I9 -> 140 | K9: Abierta
A10: INC-007 | B10: PRY-005 | C10: Equipo Beta | D10: Ana López | E10: 45708 | F10: Revisita | G10: Cliente solicita reubicación de un panel durante instalación | H10: 2 | I10: 0 | J10: =H10*'📋 Proyectos'!$E$3+I10 -> 70 | K10: En Revisión

Sheet 👥 Control Equipos
A1: 👥 CONTROL DE EQUIPOS — Rendimiento comparativo
A2: Todos los datos se calculan automáticamente desde Proyectos, Horas e Incidencias. Solo lectura.
B3: 🔵 EQUIPO ALPHA | G3: 🔵 EQUIPO BETA | L3: 🔵 EQUIPO GAMMA | Q3: 🔵 EQUIPO DELTA | V3: =IFERROR(AVERAGEIFS('📋 Proyectos'!$X:$X,'📋 Proyectos'!$E:$E,"Equipo Alpha",'📋 Proyectos'!$F:$F,"Completado"),0) -> 0
B4: 📋 Proyectos totales | E4: =COUNTIF('📋 Proyectos'!$E:$E,"Equipo Alpha") -> 3 | G4: 📋 Proyectos totales | J4: =COUNTIF('📋 Proyectos'!$E:$E,"Equipo Beta") -> 3 | L4: 📋 Proyectos totales | O4: =COUNTIF('📋 Proyectos'!$E:$E,"Equipo Gamma") -> 2 | Q4: 📋 Proyectos totales | T4: =COUNTIF('📋 Proyectos'!$E:$E,"Equipo Delta") -> 2 | V4: =IFERROR(AVERAGEIFS('📋 Proyectos'!$X:$X,'📋 Proyectos'!$E:$E,"Equipo Beta",'📋 Proyectos'!$F:$F,"Completado"),0) -> 0
B5: ✅ Completados | E5: =COUNTIFS('📋 Proyectos'!$E:$E,"Equipo Alpha",'📋 Proyectos'!$F:$F,"Completado") -> 3 | G5: ✅ Completados | J5: =COUNTIFS('📋 Proyectos'!$E:$E,"Equipo Beta",'📋 Proyectos'!$F:$F,"Completado") -> 1 | L5: ✅ Completados | O5: =COUNTIFS('📋 Proyectos'!$E:$E,"Equipo Gamma",'📋 Proyectos'!$F:$F,"Completado") -> 1 | Q5: ✅ Completados | T5: =COUNTIFS('📋 Proyectos'!$E:$E,"Equipo Delta",'📋 Proyectos'!$F:$F,"Completado") -> 1 | V5: =IFERROR(AVERAGEIFS('📋 Proyectos'!$X:$X,'📋 Proyectos'!$E:$E,"Equipo Gamma",'📋 Proyectos'!$F:$F,"Completado"),0) -> 0
B6: 🔄 En Ejecución | E6: =COUNTIFS('📋 Proyectos'!$E:$E,"Equipo Alpha",'📋 Proyectos'!$F:$F,"En Ejecución") -> 0 | G6: 🔄 En Ejecución | J6: =COUNTIFS('📋 Proyectos'!$E:$E,"Equipo Beta",'📋 Proyectos'!$F:$F,"En Ejecución") -> 1 | L6: 🔄 En Ejecución | O6: =COUNTIFS('📋 Proyectos'!$E:$E,"Equipo Gamma",'📋 Proyectos'!$F:$F,"En Ejecución") -> 1 | Q6: 🔄 En Ejecución | T6: =COUNTIFS('📋 Proyectos'!$E:$E,"Equipo Delta",'📋 Proyectos'!$F:$F,"En Ejecución") -> 0 | V6: =IFERROR(AVERAGEIFS('📋 Proyectos'!$X:$X,'📋 Proyectos'!$E:$E,"Equipo Delta",'📋 Proyectos'!$F:$F,"Completado"),0) -> 0
B7: ⏱️ Días medio por obra | E7: =IFERROR(AVERAGEIFS('📋 Proyectos'!$K:$K,'📋 Proyectos'!$E:$E,"Equipo Alpha",'📋 Proyectos'!$F:$F,"Completado"),0) -> 13 | G7: ⏱️ Días medio por obra | J7: =IFERROR(AVERAGEIFS('📋 Proyectos'!$K:$K,'📋 Proyectos'!$E:$E,"Equipo Beta",'📋 Proyectos'!$F:$F,"Completado"),0) -> 24 | L7: ⏱️ Días medio por obra | O7: =IFERROR(AVERAGEIFS('📋 Proyectos'!$K:$K,'📋 Proyectos'!$E:$E,"Equipo Gamma",'📋 Proyectos'!$F:$F,"Completado"),0) -> 11 | Q7: ⏱️ Días medio por obra | T7: =IFERROR(AVERAGEIFS('📋 Proyectos'!$K:$K,'📋 Proyectos'!$E:$E,"Equipo Delta",'📋 Proyectos'!$F:$F,"Completado"),0) -> 9
B8: 📅 Desv. tiempo (días) | E8: =IFERROR(AVERAGEIFS('📋 Proyectos'!$L:$L,'📋 Proyectos'!$E:$E,"Equipo Alpha",'📋 Proyectos'!$F:$F,"Completado"),0) -> -1 | G8: 📅 Desv. tiempo (días) | J8: =IFERROR(AVERAGEIFS('📋 Proyectos'!$L:$L,'📋 Proyectos'!$E:$E,"Equipo Beta",'📋 Proyectos'!$F:$F,"Completado"),0) -> 3 | L8: 📅 Desv. tiempo (días) | O8: =IFERROR(AVERAGEIFS('📋 Proyectos'!$L:$L,'📋 Proyectos'!$E:$E,"Equipo Gamma",'📋 Proyectos'!$F:$F,"Completado"),0) -> 2 | Q8: 📅 Desv. tiempo (días) | T8: =IFERROR(AVERAGEIFS('📋 Proyectos'!$L:$L,'📋 Proyectos'!$E:$E,"Equipo Delta",'📋 Proyectos'!$F:$F,"Completado"),0) -> 2
B9: 🔨 Horas totales MO | E9: =IFERROR(SUMIF('⏱️ Horas MO'!$C:$C,"Equipo Alpha",'⏱️ Horas MO'!$G:$G),0) -> 100 | G9: 🔨 Horas totales MO | J9: =IFERROR(SUMIF('⏱️ Horas MO'!$C:$C,"Equipo Beta",'⏱️ Horas MO'!$G:$G),0) -> 24 | L9: 🔨 Horas totales MO | O9: =IFERROR(SUMIF('⏱️ Horas MO'!$C:$C,"Equipo Gamma",'⏱️ Horas MO'!$G:$G),0) -> 32 | Q9: 🔨 Horas totales MO | T9: =IFERROR(SUMIF('⏱️ Horas MO'!$C:$C,"Equipo Delta",'⏱️ Horas MO'!$G:$G),0) -> 30
B10: 💶 Coste MO total (€) | E10: =IFERROR(SUMIF('⏱️ Horas MO'!$C:$C,"Equipo Alpha",'⏱️ Horas MO'!$I:$I),0) -> 3500 | G10: 💶 Coste MO total (€) | J10: =IFERROR(SUMIF('⏱️ Horas MO'!$C:$C,"Equipo Beta",'⏱️ Horas MO'!$I:$I),0) -> 840 | L10: 💶 Coste MO total (€) | O10: =IFERROR(SUMIF('⏱️ Horas MO'!$C:$C,"Equipo Gamma",'⏱️ Horas MO'!$I:$I),0) -> 1120 | Q10: 💶 Coste MO total (€) | T10: =IFERROR(SUMIF('⏱️ Horas MO'!$C:$C,"Equipo Delta",'⏱️ Horas MO'!$I:$I),0) -> 1050
B11: 📦 Desv. material (€) | E11: =IFERROR(SUMIFS('📋 Proyectos'!$O:$O,'📋 Proyectos'!$E:$E,"Equipo Alpha",'📋 Proyectos'!$F:$F,"Completado"),0) -> 3 | G11: 📦 Desv. material (€) | J11: =IFERROR(SUMIFS('📋 Proyectos'!$O:$O,'📋 Proyectos'!$E:$E,"Equipo Beta",'📋 Proyectos'!$F:$F,"Completado"),0) -> -3 | L11: 📦 Desv. material (€) | O11: =IFERROR(SUMIFS('📋 Proyectos'!$O:$O,'📋 Proyectos'!$E:$E,"Equipo Gamma",'📋 Proyectos'!$F:$F,"Completado"),0) -> -2 | Q11: 📦 Desv. material (€) | T11: =IFERROR(SUMIFS('📋 Proyectos'!$O:$O,'📋 Proyectos'!$E:$E,"Equipo Delta",'📋 Proyectos'!$F:$F,"Completado"),0) -> -2
B12: ⚠️ Incidencias totales | E12: =COUNTIF('⚠️ Incidencias'!$C:$C,"Equipo Alpha") -> 1 | G12: ⚠️ Incidencias totales | J12: =COUNTIF('⚠️ Incidencias'!$C:$C,"Equipo Beta") -> 3 | L12: ⚠️ Incidencias totales | O12: =COUNTIF('⚠️ Incidencias'!$C:$C,"Equipo Gamma") -> 2 | Q12: ⚠️ Incidencias totales | T12: =COUNTIF('⚠️ Incidencias'!$C:$C,"Equipo Delta") -> 1
B13: 📊 Ratio inc./proyecto | E13: =IFERROR(COUNTIF('⚠️ Incidencias'!$C:$C,"Equipo Alpha")/COUNTIFS('📋 Proyectos'!$E:$E,"Equipo Alpha",'📋 Proyectos'!$F:$F,"Completado"),0) -> 0.33333333 | G13: 📊 Ratio inc./proyecto | J13: =IFERROR(COUNTIF('⚠️ Incidencias'!$C:$C,"Equipo Beta")/COUNTIFS('📋 Proyectos'!$E:$E,"Equipo Beta",'📋 Proyectos'!$F:$F,"Completado"),0) -> 3 | L13: 📊 Ratio inc./proyecto | O13: =IFERROR(COUNTIF('⚠️ Incidencias'!$C:$C,"Equipo Gamma")/COUNTIFS('📋 Proyectos'!$E:$E,"Equipo Gamma",'📋 Proyectos'!$F:$F,"Completado"),0) -> 2 | Q13: 📊 Ratio inc./proyecto | T13: =IFERROR(COUNTIF('⚠️ Incidencias'!$C:$C,"Equipo Delta")/COUNTIFS('📋 Proyectos'!$E:$E,"Equipo Delta",'📋 Proyectos'!$F:$F,"Completado"),0) -> 1
B14: 💰 Margen total generado | E14: =IFERROR(SUMIFS('📋 Proyectos'!$W:$W,'📋 Proyectos'!$E:$E,"Equipo Alpha",'📋 Proyectos'!$F:$F,"Completado"),0) -> 0 | G14: 💰 Margen total generado | J14: =IFERROR(SUMIFS('📋 Proyectos'!$W:$W,'📋 Proyectos'!$E:$E,"Equipo Beta",'📋 Proyectos'!$F:$F,"Completado"),0) -> 0 | L14: 💰 Margen total generado | O14: =IFERROR(SUMIFS('📋 Proyectos'!$W:$W,'📋 Proyectos'!$E:$E,"Equipo Gamma",'📋 Proyectos'!$F:$F,"Completado"),0) -> 0 | Q14: 💰 Margen total generado | T14: =IFERROR(SUMIFS('📋 Proyectos'!$W:$W,'📋 Proyectos'!$E:$E,"Equipo Delta",'📋 Proyectos'!$F:$F,"Completado"),0) -> 0
B15: 📈 Margen medio % | E15: =IFERROR(AVERAGEIFS('📋 Proyectos'!$X:$X,'📋 Proyectos'!$E:$E,"Equipo Alpha",'📋 Proyectos'!$F:$F,"Completado"),0) -> 0 | G15: 📈 Margen medio % | J15: =IFERROR(AVERAGEIFS('📋 Proyectos'!$X:$X,'📋 Proyectos'!$E:$E,"Equipo Beta",'📋 Proyectos'!$F:$F,"Completado"),0) -> 0 | L15: 📈 Margen medio % | O15: =IFERROR(AVERAGEIFS('📋 Proyectos'!$X:$X,'📋 Proyectos'!$E:$E,"Equipo Gamma",'📋 Proyectos'!$F:$F,"Completado"),0) -> 0 | Q15: 📈 Margen medio % | T15: =IFERROR(AVERAGEIFS('📋 Proyectos'!$X:$X,'📋 Proyectos'!$E:$E,"Equipo Delta",'📋 Proyectos'!$F:$F,"Completado"),0) -> 0
B16: 🏆 RANKING | E16: =IFERROR(RANK(E15,$V$3:$V$6),"-") -> 1 | G16: 🏆 RANKING | J16: =IFERROR(RANK(J15,$V$3:$V$6),"-") -> 1 | L16: 🏆 RANKING | O16: =IFERROR(RANK(O15,$V$3:$V$6),"-") -> 1 | Q16: 🏆 RANKING | T16: =IFERROR(RANK(T15,$V$3:$V$6),"-") -> 1
B19: 📊 COMPARATIVA ENTRE EQUIPOS
B20: Métrica | E20: Equipo Alpha | H20: Equipo Beta | K20: Equipo Gamma | N20: Equipo Delta | Q20: 🏆 MEJOR
B21: Proyectos completados | E21: =COUNTIFS('📋 Proyectos'!$E:$E,"Equipo Alpha",'📋 Proyectos'!$F:$F,"Completado") -> 3 | H21: =COUNTIFS('📋 Proyectos'!$E:$E,"Equipo Beta",'📋 Proyectos'!$F:$F,"Completado") -> 1 | K21: =COUNTIFS('📋 Proyectos'!$E:$E,"Equipo Gamma",'📋 Proyectos'!$F:$F,"Completado") -> 1 | N21: =COUNTIFS('📋 Proyectos'!$E:$E,"Equipo Delta",'📋 Proyectos'!$F:$F,"Completado") -> 1 | Q21: =IF(MAX(E21,H21,K21,N21)=E21,"Alpha",IF(MAX(E21,H21,K21,N21)=H21,"Beta",IF(MAX(E21,H21,K21,N21)=K21,"Gamma","Delta"))) -> Alpha
B22: Desv. media tiempo (días) | E22: =IFERROR(AVERAGEIFS('📋 Proyectos'!$L:$L,'📋 Proyectos'!$E:$E,"Equipo Alpha",'📋 Proyectos'!$F:$F,"Completado"),0) -> -1 | H22: =IFERROR(AVERAGEIFS('📋 Proyectos'!$L:$L,'📋 Proyectos'!$E:$E,"Equipo Beta",'📋 Proyectos'!$F:$F,"Completado"),0) -> 3 | K22: =IFERROR(AVERAGEIFS('📋 Proyectos'!$L:$L,'📋 Proyectos'!$E:$E,"Equipo Gamma",'📋 Proyectos'!$F:$F,"Completado"),0) -> 2 | N22: =IFERROR(AVERAGEIFS('📋 Proyectos'!$L:$L,'📋 Proyectos'!$E:$E,"Equipo Delta",'📋 Proyectos'!$F:$F,"Completado"),0) -> 2 | Q22: =IF(MIN(E22,H22,K22,N22)=E22,"Alpha",IF(MIN(E22,H22,K22,N22)=H22,"Beta",IF(MIN(E22,H22,K22,N22)=K22,"Gamma","Delta"))) -> Alpha
B23: Margen medio % | E23: =IFERROR(AVERAGEIFS('📋 Proyectos'!$X:$X,'📋 Proyectos'!$E:$E,"Equipo Alpha",'📋 Proyectos'!$F:$F,"Completado"),0) -> 0 | H23: =IFERROR(AVERAGEIFS('📋 Proyectos'!$X:$X,'📋 Proyectos'!$E:$E,"Equipo Beta",'📋 Proyectos'!$F:$F,"Completado"),0) -> 0 | K23: =IFERROR(AVERAGEIFS('📋 Proyectos'!$X:$X,'📋 Proyectos'!$E:$E,"Equipo Gamma",'📋 Proyectos'!$F:$F,"Completado"),0) -> 0 | N23: =IFERROR(AVERAGEIFS('📋 Proyectos'!$X:$X,'📋 Proyectos'!$E:$E,"Equipo Delta",'📋 Proyectos'!$F:$F,"Completado"),0) -> 0 | Q23: =IF(MAX(E23,H23,K23,N23)=E23,"Alpha",IF(MAX(E23,H23,K23,N23)=H23,"Beta",IF(MAX(E23,H23,K23,N23)=K23,"Gamma","Delta"))) -> Alpha
B24: Incidencias totales | E24: =COUNTIF('⚠️ Incidencias'!$C:$C,"Equipo Alpha") -> 1 | H24: =COUNTIF('⚠️ Incidencias'!$C:$C,"Equipo Beta") -> 3 | K24: =COUNTIF('⚠️ Incidencias'!$C:$C,"Equipo Gamma") -> 2 | N24: =COUNTIF('⚠️ Incidencias'!$C:$C,"Equipo Delta") -> 1 | Q24: =IF(MIN(E24,H24,K24,N24)=E24,"Alpha",IF(MIN(E24,H24,K24,N24)=H24,"Beta",IF(MIN(E24,H24,K24,N24)=K24,"Gamma","Delta"))) -> Alpha
B25: Ratio inc./proyecto | E25: =IFERROR(COUNTIF('⚠️ Incidencias'!$C:$C,"Equipo Alpha")/COUNTIFS('📋 Proyectos'!$E:$E,"Equipo Alpha",'📋 Proyectos'!$F:$F,"Completado"),0) -> 0.33333333 | H25: =IFERROR(COUNTIF('⚠️ Incidencias'!$C:$C,"Equipo Beta")/COUNTIFS('📋 Proyectos'!$E:$E,"Equipo Beta",'📋 Proyectos'!$F:$F,"Completado"),0) -> 3 | K25: =IFERROR(COUNTIF('⚠️ Incidencias'!$C:$C,"Equipo Gamma")/COUNTIFS('📋 Proyectos'!$E:$E,"Equipo Gamma",'📋 Proyectos'!$F:$F,"Completado"),0) -> 2 | N25: =IFERROR(COUNTIF('⚠️ Incidencias'!$C:$C,"Equipo Delta")/COUNTIFS('📋 Proyectos'!$E:$E,"Equipo Delta",'📋 Proyectos'!$F:$F,"Completado"),0) -> 1 | Q25: =IF(MIN(E25,H25,K25,N25)=E25,"Alpha",IF(MIN(E25,H25,K25,N25)=H25,"Beta",IF(MIN(E25,H25,K25,N25)=K25,"Gamma","Delta"))) -> Alpha

Sheet 💰 Rentabilidad
A1: 💰 RENTABILIDAD POR PROYECTO — Qué obras nos dan más dinero
A2: Ranking automático. Columnas clave para contabilidad. Solo proyectos con datos completos aparecen rankados.
A3: Posición | B3: Nº Proyecto | C3: Cliente | D3: Tipo | E3: Equipo | F3: Precio Venta (€) | G3: Coste Material (€) | H3: Coste MO (€) | I3: Coste Total (€) | J3: Margen Bruto (€) | K3: % Margen | L3: Semáforo
A4: 1 | B4: ='📋 Proyectos'!A6 -> PRY-001 | C4: ='📋 Proyectos'!B6 -> Familia Rodríguez | D4: ='📋 Proyectos'!D6 -> Solar Residencial | E4: ='📋 Proyectos'!E6 -> Equipo Alpha | F4: ='📋 Proyectos'!U6 | G4: ='📋 Proyectos'!N6 -> 0 | H4: ='📋 Proyectos'!T6 -> 1330 | I4: ='📋 Proyectos'!V6 | J4: ='📋 Proyectos'!W6 | K4: ='📋 Proyectos'!X6 | L4: ='📋 Proyectos'!Z6 -> ⚪
A5: 2 | B5: ='📋 Proyectos'!A7 -> PRY-002 | C5: ='📋 Proyectos'!B7 -> Comunidad Sta. Ana | D5: ='📋 Proyectos'!D7 -> Solar Industrial | E5: ='📋 Proyectos'!E7 -> Equipo Beta | F5: ='📋 Proyectos'!U7 | G5: ='📋 Proyectos'!N7 -> 0 | H5: ='📋 Proyectos'!T7 -> 560 | I5: ='📋 Proyectos'!V7 | J5: ='📋 Proyectos'!W7 | K5: ='📋 Proyectos'!X7 | L5: ='📋 Proyectos'!Z7 -> ⚪
A6: 3 | B6: ='📋 Proyectos'!A8 -> PRY-003 | C6: ='📋 Proyectos'!B8 -> José M. Herrera | D6: ='📋 Proyectos'!D8 -> Aerotermia | E6: ='📋 Proyectos'!E8 -> Equipo Alpha | F6: ='📋 Proyectos'!U8 | G6: ='📋 Proyectos'!N8 -> 0 | H6: ='📋 Proyectos'!T8 -> 770 | I6: ='📋 Proyectos'!V8 | J6: ='📋 Proyectos'!W8 | K6: ='📋 Proyectos'!X8 | L6: ='📋 Proyectos'!Z8 -> ⚪
A7: 4 | B7: ='📋 Proyectos'!A9 -> PRY-004 | C7: ='📋 Proyectos'!B9 -> Nave Industrial López | D7: ='📋 Proyectos'!D9 -> Solar Industrial | E7: ='📋 Proyectos'!E9 -> Equipo Gamma | F7: ='📋 Proyectos'!U9 | G7: ='📋 Proyectos'!N9 -> 0 | H7: ='📋 Proyectos'!T9 -> 560 | I7: ='📋 Proyectos'!V9 | J7: ='📋 Proyectos'!W9 | K7: ='📋 Proyectos'!X9 | L7: ='📋 Proyectos'!Z9 -> ⚪
A8: 5 | B8: ='📋 Proyectos'!A10 -> PRY-005 | C8: ='📋 Proyectos'!B10 -> Hotel Mediterráneo | D8: ='📋 Proyectos'!D10 -> Mixto Solar+Aero | E8: ='📋 Proyectos'!E10 -> Equipo Beta | F8: ='📋 Proyectos'!U10 | G8: ='📋 Proyectos'!N10 -> 0 | H8: ='📋 Proyectos'!T10 -> 280 | I8: ='📋 Proyectos'!V10 | J8: ='📋 Proyectos'!W10 | K8: ='📋 Proyectos'!X10 | L8: ='📋 Proyectos'!Z10 -> ⚪
A9: 6 | B9: ='📋 Proyectos'!A11 -> PRY-006 | C9: ='📋 Proyectos'!B11 -> Clínica Dental Pérez | D9: ='📋 Proyectos'!D11 -> Calefacción | E9: ='📋 Proyectos'!E11 -> Equipo Delta | F9: ='📋 Proyectos'!U11 | G9: ='📋 Proyectos'!N11 -> 0 | H9: ='📋 Proyectos'!T11 -> 1050 | I9: ='📋 Proyectos'!V11 | J9: ='📋 Proyectos'!W11 | K9: ='📋 Proyectos'!X11 | L9: ='📋 Proyectos'!Z11 -> ⚪
A10: 7 | B10: ='📋 Proyectos'!A12 -> PRY-007 | C10: ='📋 Proyectos'!B12 -> Polideportivo Municipal | D10: ='📋 Proyectos'!D12 -> Solar Industrial | E10: ='📋 Proyectos'!E12 -> Equipo Alpha | F10: ='📋 Proyectos'!U12 | G10: ='📋 Proyectos'!N12 -> 0 | H10: ='📋 Proyectos'!T12 -> 1400 | I10: ='📋 Proyectos'!V12 | J10: ='📋 Proyectos'!W12 | K10: ='📋 Proyectos'!X12 | L10: ='📋 Proyectos'!Z12 -> ⚪
A11: 8 | B11: ='📋 Proyectos'!A13 -> PRY-008 | C11: ='📋 Proyectos'!B13 -> Residencia 3ª Edad | D11: ='📋 Proyectos'!D13 -> Aerotermia | E11: ='📋 Proyectos'!E13 -> Equipo Gamma | F11: ='📋 Proyectos'!U13 | G11: ='📋 Proyectos'!N13 -> 0 | H11: ='📋 Proyectos'!T13 -> 560 | I11: ='📋 Proyectos'!V13 | J11: ='📋 Proyectos'!W13 | K11: ='📋 Proyectos'!X13 | L11: ='📋 Proyectos'!Z13 -> ⚪
A12: 9 | B12: ='📋 Proyectos'!A14 -> PRY-009 | C12: ='📋 Proyectos'!B14 -> Chalet García-Vega | D12: ='📋 Proyectos'!D14 -> Solar Residencial | E12: ='📋 Proyectos'!E14 -> Equipo Delta | F12: ='📋 Proyectos'!U14 | G12: ='📋 Proyectos'!N14 -> 0 | H12: ='📋 Proyectos'!T14 | I12: ='📋 Proyectos'!V14 | J12: ='📋 Proyectos'!W14 | K12: ='📋 Proyectos'!X14 | L12: ='📋 Proyectos'!Z14 -> ⚪
A13: 10 | B13: ='📋 Proyectos'!A15 -> PRY-010 | C13: ='📋 Proyectos'!B15 -> Fábrica Textil Norte | D13: ='📋 Proyectos'!D15 -> Solar Industrial | E13: ='📋 Proyectos'!E15 -> Equipo Beta | F13: ='📋 Proyectos'!U15 | G13: ='📋 Proyectos'!N15 -> 0 | H13: ='📋 Proyectos'!T15 | I13: ='📋 Proyectos'!V15 | J13: ='📋 Proyectos'!W15 | K13: ='📋 Proyectos'!X15 | L13: ='📋 Proyectos'!Z15 -> ⚪
A16: 📊 RESUMEN FINANCIERO POR TIPO DE INSTALACIÓN
A17: Tipo Instalación | B17: Nº Proyectos Completados | C17: Facturación Total (€) | D17: Coste Material Total (€) | E17: Coste MO Total (€) | F17: Margen Total (€) | G17: Margen Medio %
A18: Solar Residencial | B18: =COUNTIFS('📋 Proyectos'!$D:$D,"Solar Residencial",'📋 Proyectos'!$F:$F,"Completado") -> 1 | C18: =IFERROR(SUMIFS('📋 Proyectos'!$U:$U,'📋 Proyectos'!$D:$D,"Solar Residencial",'📋 Proyectos'!$F:$F,"Completado"),0) -> 0 | D18: =IFERROR(SUMIFS('📋 Proyectos'!$N:$N,'📋 Proyectos'!$D:$D,"Solar Residencial",'📋 Proyectos'!$F:$F,"Completado"),0) -> 0 | E18: =IFERROR(SUMIFS('📋 Proyectos'!$T:$T,'📋 Proyectos'!$D:$D,"Solar Residencial",'📋 Proyectos'!$F:$F,"Completado"),0) -> 1330 | F18: =IFERROR(SUMIFS('📋 Proyectos'!$W:$W,'📋 Proyectos'!$D:$D,"Solar Residencial",'📋 Proyectos'!$F:$F,"Completado"),0) -> 0 | G18: =IFERROR(AVERAGEIFS('📋 Proyectos'!$X:$X,'📋 Proyectos'!$D:$D,"Solar Residencial",'📋 Proyectos'!$F:$F,"Completado"),0) -> 0
A19: Solar Industrial | B19: =COUNTIFS('📋 Proyectos'!$D:$D,"Solar Industrial",'📋 Proyectos'!$F:$F,"Completado") -> 2 | C19: =IFERROR(SUMIFS('📋 Proyectos'!$U:$U,'📋 Proyectos'!$D:$D,"Solar Industrial",'📋 Proyectos'!$F:$F,"Completado"),0) -> 0 | D19: =IFERROR(SUMIFS('📋 Proyectos'!$N:$N,'📋 Proyectos'!$D:$D,"Solar Industrial",'📋 Proyectos'!$F:$F,"Completado"),0) -> 0 | E19: =IFERROR(SUMIFS('📋 Proyectos'!$T:$T,'📋 Proyectos'!$D:$D,"Solar Industrial",'📋 Proyectos'!$F:$F,"Completado"),0) -> 1960 | F19: =IFERROR(SUMIFS('📋 Proyectos'!$W:$W,'📋 Proyectos'!$D:$D,"Solar Industrial",'📋 Proyectos'!$F:$F,"Completado"),0) -> 0 | G19: =IFERROR(AVERAGEIFS('📋 Proyectos'!$X:$X,'📋 Proyectos'!$D:$D,"Solar Industrial",'📋 Proyectos'!$F:$F,"Completado"),0) -> 0
A20: Aerotermia | B20: =COUNTIFS('📋 Proyectos'!$D:$D,"Aerotermia",'📋 Proyectos'!$F:$F,"Completado") -> 2 | C20: =IFERROR(SUMIFS('📋 Proyectos'!$U:$U,'📋 Proyectos'!$D:$D,"Aerotermia",'📋 Proyectos'!$F:$F,"Completado"),0) -> 0 | D20: =IFERROR(SUMIFS('📋 Proyectos'!$N:$N,'📋 Proyectos'!$D:$D,"Aerotermia",'📋 Proyectos'!$F:$F,"Completado"),0) -> 0 | E20: =IFERROR(SUMIFS('📋 Proyectos'!$T:$T,'📋 Proyectos'!$D:$D,"Aerotermia",'📋 Proyectos'!$F:$F,"Completado"),0) -> 1330 | F20: =IFERROR(SUMIFS('📋 Proyectos'!$W:$W,'📋 Proyectos'!$D:$D,"Aerotermia",'📋 Proyectos'!$F:$F,"Completado"),0) -> 0 | G20: =IFERROR(AVERAGEIFS('📋 Proyectos'!$X:$X,'📋 Proyectos'!$D:$D,"Aerotermia",'📋 Proyectos'!$F:$F,"Completado"),0) -> 0
A21: Calefacción | B21: =COUNTIFS('📋 Proyectos'!$D:$D,"Calefacción",'📋 Proyectos'!$F:$F,"Completado") -> 1 | C21: =IFERROR(SUMIFS('📋 Proyectos'!$U:$U,'📋 Proyectos'!$D:$D,"Calefacción",'📋 Proyectos'!$F:$F,"Completado"),0) -> 0 | D21: =IFERROR(SUMIFS('📋 Proyectos'!$N:$N,'📋 Proyectos'!$D:$D,"Calefacción",'📋 Proyectos'!$F:$F,"Completado"),0) -> 0 | E21: =IFERROR(SUMIFS('📋 Proyectos'!$T:$T,'📋 Proyectos'!$D:$D,"Calefacción",'📋 Proyectos'!$F:$F,"Completado"),0) -> 1050 | F21: =IFERROR(SUMIFS('📋 Proyectos'!$W:$W,'📋 Proyectos'!$D:$D,"Calefacción",'📋 Proyectos'!$F:$F,"Completado"),0) -> 0 | G21: =IFERROR(AVERAGEIFS('📋 Proyectos'!$X:$X,'📋 Proyectos'!$D:$D,"Calefacción",'📋 Proyectos'!$F:$F,"Completado"),0) -> 0
A22: Mixto Solar+Aero | B22: =COUNTIFS('📋 Proyectos'!$D:$D,"Mixto Solar+Aero",'📋 Proyectos'!$F:$F,"Completado") -> 0 | C22: =IFERROR(SUMIFS('📋 Proyectos'!$U:$U,'📋 Proyectos'!$D:$D,"Mixto Solar+Aero",'📋 Proyectos'!$F:$F,"Completado"),0) -> 0 | D22: =IFERROR(SUMIFS('📋 Proyectos'!$N:$N,'📋 Proyectos'!$D:$D,"Mixto Solar+Aero",'📋 Proyectos'!$F:$F,"Completado"),0) -> 0 | E22: =IFERROR(SUMIFS('📋 Proyectos'!$T:$T,'📋 Proyectos'!$D:$D,"Mixto Solar+Aero",'📋 Proyectos'!$F:$F,"Completado"),0) -> 0 | F22: =IFERROR(SUMIFS('📋 Proyectos'!$W:$W,'📋 Proyectos'!$D:$D,"Mixto Solar+Aero",'📋 Proyectos'!$F:$F,"Completado"),0) -> 0 | G22: =IFERROR(AVERAGEIFS('📋 Proyectos'!$X:$X,'📋 Proyectos'!$D:$D,"Mixto Solar+Aero",'📋 Proyectos'!$F:$F,"Completado"),0) -> 0
A23: TOTAL | C23: =SUM(C18:C22) -> 0 | D23: =SUM(D18:D22) -> 0 | E23: =SUM(E18:E22) -> 5670 | F23: =SUM(F18:F22) -> 0 | G23: =SUM(G18:G22) -> 0

Sheet 📐 Plantillas Presupuesto
A1: 📐 PLANTILLAS DE PRESUPUESTO — Estándares por tipo de instalación
A2: Referencia de materiales y horas estándar. n8n usa esta hoja para validar desviaciones automáticamente.
A3: Tarifa MO (€/h): | C3: 35 | D3: Margen mín: | F3: 0.2 | G3: % merma: | I3: 0.05 | J3: Contingencia: | L3: 0.08
A4: ⚙️ MATERIALES ESTÁNDAR POR TIPO DE INSTALACIÓN
A5: Tipo | B5: REF | C5: Descripción | D5: Ud. | E5: Cant. Base | F5: P.Coste (€) | G5: Subtotal (€) | H5: + Merma (€) | I5: Total c/merma (€) | J5: Horas MO | K5: Coste MO (€) | L5: Cant.Mín | M5: Cant.Máx | N5: Crítico | O5: Nota
A6: Solar Residencial | B6: SOL-001 | C6: Panel Solar Mono 400W | D6: Ud. | E6: 12 | F6: 180 | G6: =E6*F6 -> 2160 | H6: =G6*$I$3 -> 108 | I6: =G6+H6 -> 2268 | J6: 16 | K6: =J6*$C$3 -> 560 | L6: 10 | M6: 16 | N6: SÍ | O6: Base 4.8kWp
A7: Solar Residencial | B7: INV-001 | C7: Inversor Monofásico 3kW | D7: Ud. | E7: 1 | F7: 850 | G7: =E7*F7 -> 850 | H7: =G7*$I$3 -> 42.5 | I7: =G7+H7 -> 892.5 | J7: 4 | K7: =J7*$C$3 -> 140 | L7: 1 | M7: 2 | N7: SÍ | O7: 1 inv/12 paneles
A8: Solar Residencial | B8: EST-001 | C8: Estructura Tejado Inclinado | D8: Kit | E8: 3 | F8: 120 | G8: =E8*F8 -> 360 | H8: =G8*$I$3 -> 18 | I8: =G8+H8 -> 378 | J8: 6 | K8: =J8*$C$3 -> 210 | L8: 2 | M8: 5 | N8: NO | O8: 1 kit/4 paneles
A9: Solar Residencial | B9: CAB-001 | C9: Cable Solar 4mm² | D9: m | E9: 80 | F9: 0.85 | G9: =E9*F9 -> 68 | H9: =G9*$I$3 -> 3.4 | I9: =G9+H9 -> 71.4 | J9: 0 | K9: =J9*$C$3 -> 0 | L9: 60 | M9: 120 | N9: NO | O9: 10% extra incluido
A10: Solar Residencial | B10: PRO-001 | C10: Protección DC 1000V | D10: Ud. | E10: 1 | F10: 45 | G10: =E10*F10 -> 45 | H10: =G10*$I$3 -> 2.25 | I10: =G10+H10 -> 47.25 | J10: 1 | K10: =J10*$C$3 -> 35 | L10: 1 | M10: 2 | N10: SÍ
A11: Solar Residencial | B11: PRO-002 | C11: Contador Bidireccional | D11: Ud. | E11: 1 | F11: 120 | G11: =E11*F11 -> 120 | H11: =G11*$I$3 -> 6 | I11: =G11+H11 -> 126 | J11: 2 | K11: =J11*$C$3 -> 70 | L11: 1 | M11: 1 | N11: SÍ | O11: Obligatorio normativa
A12: Solar Industrial | B12: SOL-003 | C12: Panel Solar Bifacial 500W | D12: Ud. | E12: 60 | F12: 250 | G12: =E12*F12 -> 15000 | H12: =G12*$I$3 -> 750 | I12: =G12+H12 -> 15750 | J12: 80 | K12: =J12*$C$3 -> 2800 | L12: 50 | M12: 100 | N12: SÍ | O12: Base 30kWp
A13: Solar Industrial | B13: INV-003 | C13: Inversor Trifásico 10kW | D13: Ud. | E13: 3 | F13: 1800 | G13: =E13*F13 -> 5400 | H13: =G13*$I$3 -> 270 | I13: =G13+H13 -> 5670 | J13: 12 | K13: =J13*$C$3 -> 420 | L13: 2 | M13: 6 | N13: SÍ | O13: 1 inv/20 paneles
A14: Solar Industrial | B14: EST-002 | C14: Estructura Cubierta Plana | D14: Kit | E14: 15 | F14: 145 | G14: =E14*F14 -> 2175 | H14: =G14*$I$3 -> 108.75 | I14: =G14+H14 -> 2283.75 | J14: 20 | K14: =J14*$C$3 -> 700 | L14: 10 | M14: 25 | N14: NO
A15: Solar Industrial | B15: CAB-002 | C15: Cable Solar 6mm² | D15: m | E15: 400 | F15: 1.2 | G15: =E15*F15 -> 480 | H15: =G15*$I$3 -> 24 | I15: =G15+H15 -> 504 | J15: 0 | K15: =J15*$C$3 -> 0 | L15: 300 | M15: 600 | N15: NO
A16: Solar Industrial | B16: BAT-002 | C16: Batería LiFePO4 10kWh | D16: Ud. | E16: 2 | F16: 4100 | G16: =E16*F16 -> 8200 | H16: =G16*$I$3 -> 410 | I16: =G16+H16 -> 8610 | J16: 4 | K16: =J16*$C$3 -> 140 | L16: 0 | M16: 4 | N16: NO | O16: Opcional
A17: Aerotermia | B17: AER-001 | C17: Aerotermia 8kW Monobloc | D17: Ud. | E17: 1 | F17: 1900 | G17: =E17*F17 -> 1900 | H17: =G17*$I$3 -> 95 | I17: =G17+H17 -> 1995 | J17: 8 | K17: =J17*$C$3 -> 280 | L17: 1 | M17: 1 | N17: SÍ | O17: Hasta 150m²
A18: Aerotermia | B18: TUB-002 | C18: Tubería Cobre 22mm | D18: m | E18: 25 | F18: 8.5 | G18: =E18*F18 -> 212.5 | H18: =G18*$I$3 -> 10.625 | I18: =G18+H18 -> 223.125 | J18: 4 | K18: =J18*$C$3 -> 140 | L18: 15 | M18: 40 | N18: NO
A19: Aerotermia | B19: TUB-001 | C19: Tubo Corrugado PG29 | D19: m | E19: 20 | F19: 0.55 | G19: =E19*F19 -> 11 | H19: =G19*$I$3 -> 0.55 | I19: =G19+H19 -> 11.55 | J19: 0 | K19: =J19*$C$3 -> 0 | L19: 15 | M19: 30 | N19: NO
A20: Calefacción | B20: CAL-001 | C20: Caldera Gas Condensación | D20: Ud. | E20: 1 | F20: 750 | G20: =E20*F20 -> 750 | H20: =G20*$I$3 -> 37.5 | I20: =G20+H20 -> 787.5 | J20: 8 | K20: =J20*$C$3 -> 280 | L20: 1 | M20: 1 | N20: SÍ
A21: Calefacción | B21: CAL-002 | C21: Radiador Aluminio 10 elem. | D21: Ud. | E21: 8 | F21: 85 | G21: =E21*F21 -> 680 | H21: =G21*$I$3 -> 34 | I21: =G21+H21 -> 714 | J21: 2 | K21: =J21*$C$3 -> 70 | L21: 6 | M21: 12 | N21: NO | O21: Media 8/vivienda
A22: Calefacción | B22: TUB-001 | C22: Tubo Corrugado PG29 | D22: m | E22: 30 | F22: 0.55 | G22: =E22*F22 -> 16.5 | H22: =G22*$I$3 -> 0.825 | I22: =G22+H22 -> 17.325 | J22: 0 | K22: =J22*$C$3 -> 0 | L22: 20 | M22: 50 | N22: NO
A24: TOTAL MATERIAL — Solar Residencial | G24: =SUM(G6:G11) -> 3603 | I24: =SUM(I6:I11) -> 3783.15 | J24: =SUM(J6:J11) -> 29 | K24: =SUM(K6:K11) -> 1015
A26: TOTAL MATERIAL — Solar Industrial | G26: =SUM(G12:G16) -> 31255 | I26: =SUM(I12:I16) -> 32817.75 | J26: =SUM(J12:J16) -> 116 | K26: =SUM(K12:K16) -> 4060
A28: TOTAL MATERIAL — Aerotermia | G28: =SUM(G17:G19) -> 2123.5 | I28: =SUM(I17:I19) -> 2229.675 | J28: =SUM(J17:J19) -> 12 | K28: =SUM(K17:K19) -> 420
A30: TOTAL MATERIAL — Calefacción | G30: =SUM(G20:G22) -> 1446.5 | I30: =SUM(I20:I22) -> 1518.825 | J30: =SUM(J20:J22) -> 10 | K30: =SUM(K20:K22) -> 350

Sheet 🔧 Garantías y Mantenimiento
A1: 🔧 GARANTÍAS & MANTENIMIENTO — Control postventa y contratos recurrentes
A2: n8n revisa esta hoja cada lunes y lanza alertas automáticas de vencimientos. Los contratos de mantenimiento son ingresos recurrentes.
A3: Nº Proyecto | B3: Cliente | C3: Tipo Inst. | D3: Equipo | E3: Fecha Inst. | F3: Fin Garantía Fabricante | G3: Fin Garantía Instalación | H3: Días para Vencer | I3: Contrato Manto | J3: Precio Anual Manto (€) | K3: Próxima Revisión | L3: Revisiones Realizadas | M3: Coste Última Revisión (€) | N3: Estado | O3: Alerta n8n | P3: Notas
A4: PRY-001 | B4: Familia Rodríguez | C4: Solar Residencial | D4: Equipo Alpha | E4: 45678 | F4: 49330 | G4: 46408 | H4: =IF(G4="","",G4-TODAY()) -> 322 | I4: SÍ | J4: 180 | K4: 45859 | L4: 0 | N4: =IF(H4="","",IF(H4<0,"🔴 VENCIDA",IF(H4<=30,"🟠 URGENTE <30d",IF(H4<=90,"🟡 PRÓXIMA <90d","🟢 OK")))) -> 🟢 OK | O4: =IF(H4="","",IF(H4<=90,"⚡ ALERTA ACTIVA","✓ Sin alerta")) -> ✓ Sin alerta | P4: Contrato anual
A5: PRY-002 | B5: Comunidad Sta. Ana | C5: Solar Industrial | D5: Equipo Beta | E5: 45696 | F5: 49348 | G5: 46426 | H5: =IF(G5="","",G5-TODAY()) -> 340 | I5: SÍ | J5: 1200 | K5: 45877 | L5: 0 | N5: =IF(H5="","",IF(H5<0,"🔴 VENCIDA",IF(H5<=30,"🟠 URGENTE <30d",IF(H5<=90,"🟡 PRÓXIMA <90d","🟢 OK")))) -> 🟢 OK | O5: =IF(H5="","",IF(H5<=90,"⚡ ALERTA ACTIVA","✓ Sin alerta")) -> ✓ Sin alerta | P5: Tarifa especial comunidad
A6: PRY-003 | B6: José M. Herrera | C6: Aerotermia | D6: Equipo Alpha | E6: 45683 | F6: 47509 | G6: 46413 | H6: =IF(G6="","",G6-TODAY()) -> 327 | I6: SÍ | J6: 220 | K6: 45864 | L6: 0 | N6: =IF(H6="","",IF(H6<0,"🔴 VENCIDA",IF(H6<=30,"🟠 URGENTE <30d",IF(H6<=90,"🟡 PRÓXIMA <90d","🟢 OK")))) -> 🟢 OK | O6: =IF(H6="","",IF(H6<=90,"⚡ ALERTA ACTIVA","✓ Sin alerta")) -> ✓ Sin alerta
A7: PRY-006 | B7: Clínica Dental Pérez | C7: Calefacción | D7: Equipo Delta | E7: 45671 | F7: 47497 | G7: 46036 | H7: =IF(G7="","",G7-TODAY()) -> -50 | I7: SÍ | J7: 150 | K7: 45852 | L7: 0 | N7: =IF(H7="","",IF(H7<0,"🔴 VENCIDA",IF(H7<=30,"🟠 URGENTE <30d",IF(H7<=90,"🟡 PRÓXIMA <90d","🟢 OK")))) -> 🔴 VENCIDA | O7: =IF(H7="","",IF(H7<=90,"⚡ ALERTA ACTIVA","✓ Sin alerta")) -> ⚡ ALERTA ACTIVA | P7: Revisión semestral obligatoria
A8: PRY-007 | B8: Polideportivo Mun. | C8: Solar Industrial | D8: Equipo Alpha | E8: 45705 | F8: 49357 | G8: 46435 | H8: =IF(G8="","",G8-TODAY()) -> 349 | I8: SÍ | J8: 850 | K8: 45886 | L8: 0 | N8: =IF(H8="","",IF(H8<0,"🔴 VENCIDA",IF(H8<=30,"🟠 URGENTE <30d",IF(H8<=90,"🟡 PRÓXIMA <90d","🟢 OK")))) -> 🟢 OK | O8: =IF(H8="","",IF(H8<=90,"⚡ ALERTA ACTIVA","✓ Sin alerta")) -> ✓ Sin alerta | P8: Contrato premium
A9: PRY-008 | B9: Residencia 3ª Edad | C9: Aerotermia | D9: Equipo Gamma | E9: 45700 | F9: 47526 | G9: 46430 | H9: =IF(G9="","",G9-TODAY()) -> 344 | I9: SÍ | J9: 380 | K9: 45881 | L9: 0 | N9: =IF(H9="","",IF(H9<0,"🔴 VENCIDA",IF(H9<=30,"🟠 URGENTE <30d",IF(H9<=90,"🟡 PRÓXIMA <90d","🟢 OK")))) -> 🟢 OK | O9: =IF(H9="","",IF(H9<=90,"⚡ ALERTA ACTIVA","✓ Sin alerta")) -> ✓ Sin alerta
H10: =IF(G10="","",G10-TODAY()) | N10: =IF(H10="","",IF(H10<0,"🔴 VENCIDA",IF(H10<=30,"🟠 URGENTE <30d",IF(H10<=90,"🟡 PRÓXIMA <90d","🟢 OK")))) | O10: =IF(H10="","",IF(H10<=90,"⚡ ALERTA ACTIVA","✓ Sin alerta"))
H11: =IF(G11="","",G11-TODAY()) | N11: =IF(H11="","",IF(H11<0,"🔴 VENCIDA",IF(H11<=30,"🟠 URGENTE <30d",IF(H11<=90,"🟡 PRÓXIMA <90d","🟢 OK")))) | O11: =IF(H11="","",IF(H11<=90,"⚡ ALERTA ACTIVA","✓ Sin alerta"))
H12: =IF(G12="","",G12-TODAY()) | N12: =IF(H12="","",IF(H12<0,"🔴 VENCIDA",IF(H12<=30,"🟠 URGENTE <30d",IF(H12<=90,"🟡 PRÓXIMA <90d","🟢 OK")))) | O12: =IF(H12="","",IF(H12<=90,"⚡ ALERTA ACTIVA","✓ Sin alerta"))
A13: 📊 RESUMEN CONTRATOS DE MANTENIMIENTO
A14: Contratos activos | E14: Ingresos recurrentes/año | I14: Garantías urgentes <30d | M14: Garantías vencidas
A15: =COUNTIF(I4:I200,"SÍ") -> 6 | E15: =SUMIF(I4:I200,"SÍ",J4:J200) -> 2980 | I15: =COUNTIF(H4:H200,"<30")-COUNTIF(H4:H200,"<0") -> 0 | M15: =COUNTIF(H4:H200,"<0") -> 1
H16: =IF(G16="","",G16-TODAY()) | N16: =IF(H16="","",IF(H16<0,"🔴 VENCIDA",IF(H16<=30,"🟠 URGENTE <30d",IF(H16<=90,"🟡 PRÓXIMA <90d","🟢 OK")))) | O16: =IF(H16="","",IF(H16<=90,"⚡ ALERTA ACTIVA","✓ Sin alerta"))
H17: =IF(G17="","",G17-TODAY()) | N17: =IF(H17="","",IF(H17<0,"🔴 VENCIDA",IF(H17<=30,"🟠 URGENTE <30d",IF(H17<=90,"🟡 PRÓXIMA <90d","🟢 OK")))) | O17: =IF(H17="","",IF(H17<=90,"⚡ ALERTA ACTIVA","✓ Sin alerta"))
H18: =IF(G18="","",G18-TODAY()) | N18: =IF(H18="","",IF(H18<0,"🔴 VENCIDA",IF(H18<=30,"🟠 URGENTE <30d",IF(H18<=90,"🟡 PRÓXIMA <90d","🟢 OK")))) | O18: =IF(H18="","",IF(H18<=90,"⚡ ALERTA ACTIVA","✓ Sin alerta"))
H19: =IF(G19="","",G19-TODAY()) | N19: =IF(H19="","",IF(H19<0,"🔴 VENCIDA",IF(H19<=30,"🟠 URGENTE <30d",IF(H19<=90,"🟡 PRÓXIMA <90d","🟢 OK")))) | O19: =IF(H19="","",IF(H19<=90,"⚡ ALERTA ACTIVA","✓ Sin alerta"))
H20: =IF(G20="","",G20-TODAY()) | N20: =IF(H20="","",IF(H20<0,"🔴 VENCIDA",IF(H20<=30,"🟠 URGENTE <30d",IF(H20<=90,"🟡 PRÓXIMA <90d","🟢 OK")))) | O20: =IF(H20="","",IF(H20<=90,"⚡ ALERTA ACTIVA","✓ Sin alerta"))
H21: =IF(G21="","",G21-TODAY()) | N21: =IF(H21="","",IF(H21<0,"🔴 VENCIDA",IF(H21<=30,"🟠 URGENTE <30d",IF(H21<=90,"🟡 PRÓXIMA <90d","🟢 OK")))) | O21: =IF(H21="","",IF(H21<=90,"⚡ ALERTA ACTIVA","✓ Sin alerta"))
H22: =IF(G22="","",G22-TODAY()) | N22: =IF(H22="","",IF(H22<0,"🔴 VENCIDA",IF(H22<=30,"🟠 URGENTE <30d",IF(H22<=90,"🟡 PRÓXIMA <90d","🟢 OK")))) | O22: =IF(H22="","",IF(H22<=90,"⚡ ALERTA ACTIVA","✓ Sin alerta"))
H23: =IF(G23="","",G23-TODAY()) | N23: =IF(H23="","",IF(H23<0,"🔴 VENCIDA",IF(H23<=30,"🟠 URGENTE <30d",IF(H23<=90,"🟡 PRÓXIMA <90d","🟢 OK")))) | O23: =IF(H23="","",IF(H23<=90,"⚡ ALERTA ACTIVA","✓ Sin alerta"))
H24: =IF(G24="","",G24-TODAY()) | N24: =IF(H24="","",IF(H24<0,"🔴 VENCIDA",IF(H24<=30,"🟠 URGENTE <30d",IF(H24<=90,"🟡 PRÓXIMA <90d","🟢 OK")))) | O24: =IF(H24="","",IF(H24<=90,"⚡ ALERTA ACTIVA","✓ Sin alerta"))
H25: =IF(G25="","",G25-TODAY()) | N25: =IF(H25="","",IF(H25<0,"🔴 VENCIDA",IF(H25<=30,"🟠 URGENTE <30d",IF(H25<=90,"🟡 PRÓXIMA <90d","🟢 OK")))) | O25: =IF(H25="","",IF(H25<=90,"⚡ ALERTA ACTIVA","✓ Sin alerta"))
H26: =IF(G26="","",G26-TODAY()) | N26: =IF(H26="","",IF(H26<0,"🔴 VENCIDA",IF(H26<=30,"🟠 URGENTE <30d",IF(H26<=90,"🟡 PRÓXIMA <90d","🟢 OK")))) | O26: =IF(H26="","",IF(H26<=90,"⚡ ALERTA ACTIVA","✓ Sin alerta"))
H27: =IF(G27="","",G27-TODAY()) | N27: =IF(H27="","",IF(H27<0,"🔴 VENCIDA",IF(H27<=30,"🟠 URGENTE <30d",IF(H27<=90,"🟡 PRÓXIMA <90d","🟢 OK")))) | O27: =IF(H27="","",IF(H27<=90,"⚡ ALERTA ACTIVA","✓ Sin alerta"))
... H199: =IF(G199="","",G199-TODAY()) | N199: =IF(H199="","",IF(H199<0,"🔴 VENCIDA",IF(H199<=30,"🟠 URGENTE <30d",IF(H199<=90,"🟡 PRÓXIMA <90d","🟢 OK")))) | O199: =IF(H199="","",IF(H199<=90,"⚡ ALERTA ACTIVA","✓ Sin alerta"))

Sheet 🛒 Previsión Compras
A1: 🛒 PREVISIÓN DE COMPRAS — Material necesario para proyectos activos
A2: n8n actualiza esta hoja cada noche y envía el email de pedido sugerido al proveedor cuando hay urgencias.
A3: Horizonte previsión (días): | D3: 60 | E3: ← Cambiar para ajustar el horizonte temporal de la previsión
A4: 📦 NECESIDADES DE MATERIAL — Proyectos activos en los próximos 60 días
A5: REF | B5: Descripción | C5: Categoría | D5: Stock Actual | E5: Stock Mínimo | F5: Consumo Proyectado | G5: Stock Resultante | H5: Uds. a Pedir | I5: Precio Coste (€) | J5: Importe Pedido (€) | K5: Proveedor Habitual | L5: Plazo Entrega | M5: Urgencia | N5: Pedido Generado | O5: Fecha Sugerida | P5: Nota n8n
A6: SOL-001 | B6: Panel Solar Mono 400W | C6: Placas Solares | D6: =IFERROR(VLOOKUP(A6,'📊 Stock Actual'!$A:$H,8,0),0) -> 70 | E6: =IFERROR(VLOOKUP(A6,'📊 Stock Actual'!$A:$I,9,0),0) -> 10 | F6: 22 | G6: =D6-F6 -> 48 | H6: =IF(G6>=E6,0,MAX(0,E6-G6+ROUND(F6*0.15,0))) -> 0 | I6: 180 | J6: =IF(H6=0,"",H6*I6) | K6: Jinko Solar SL | L6: 7 días | M6: 🔴 URGENTE | N6: NO | O6: =IF(H6=0,"N/A",TODAY()+7) -> N/A | P6: PRY-004+PRY-005
A7: SOL-002 | B7: Panel Solar Mono 450W | C7: Placas Solares | D7: =IFERROR(VLOOKUP(A7,'📊 Stock Actual'!$A:$H,8,0),0) -> 45 | E7: =IFERROR(VLOOKUP(A7,'📊 Stock Actual'!$A:$I,9,0),0) -> 10 | F7: 15 | G7: =D7-F7 -> 30 | H7: =IF(G7>=E7,0,MAX(0,E7-G7+ROUND(F7*0.15,0))) -> 0 | I7: 210 | J7: =IF(H7=0,"",H7*I7) | K7: Longi Solar | L7: 7 días | M7: 🟠 ALTA | N7: NO | O7: =IF(H7=0,"N/A",TODAY()+7) -> N/A | P7: PRY-005
A8: INV-002 | B8: Inversor Monofásico 5kW | C8: Inversores | D8: =IFERROR(VLOOKUP(A8,'📊 Stock Actual'!$A:$H,8,0),0) -> 9 | E8: =IFERROR(VLOOKUP(A8,'📊 Stock Actual'!$A:$I,9,0),0) -> 3 | F8: 3 | G8: =D8-F8 -> 6 | H8: =IF(G8>=E8,0,MAX(0,E8-G8+ROUND(F8*0.15,0))) -> 0 | I8: 980 | J8: =IF(H8=0,"",H8*I8) | K8: Fronius Iberia | L8: 5 días | M8: 🟠 ALTA | N8: NO | O8: =IF(H8=0,"N/A",TODAY()+7) -> N/A | P8: PRY-004
A9: AER-001 | B9: Aerotermia 8kW Monobloc | C9: Aerotermia | D9: =IFERROR(VLOOKUP(A9,'📊 Stock Actual'!$A:$H,8,0),0) -> 9 | E9: =IFERROR(VLOOKUP(A9,'📊 Stock Actual'!$A:$I,9,0),0) -> 2 | F9: 2 | G9: =D9-F9 -> 7 | H9: =IF(G9>=E9,0,MAX(0,E9-G9+ROUND(F9*0.15,0))) -> 0 | I9: 1900 | J9: =IF(H9=0,"",H9*I9) | K9: Mitsubishi ES | L9: 10 días | M9: 🟡 MEDIA | N9: NO | O9: =IF(H9=0,"N/A",TODAY()+7) -> N/A | P9: PRY-005
A10: CAB-001 | B10: Cable Solar 4mm² | C10: Cableado | D10: =IFERROR(VLOOKUP(A10,'📊 Stock Actual'!$A:$H,8,0),0) -> 1450 | E10: =IFERROR(VLOOKUP(A10,'📊 Stock Actual'!$A:$I,9,0),0) -> 500 | F10: 350 | G10: =D10-F10 -> 1100 | H10: =IF(G10>=E10,0,MAX(0,E10-G10+ROUND(F10*0.15,0))) -> 0 | I10: 0.85 | J10: =IF(H10=0,"",H10*I10) | K10: Prysmian Group | L10: 3 días | M10: 🟡 MEDIA | N10: NO | O10: =IF(H10=0,"N/A",TODAY()+7) -> N/A | P10: Varios proyectos
A11: EST-001 | B11: Estructura Tejado Inclinado | C11: Estructuras | D11: =IFERROR(VLOOKUP(A11,'📊 Stock Actual'!$A:$H,8,0),0) -> 20 | E11: =IFERROR(VLOOKUP(A11,'📊 Stock Actual'!$A:$I,9,0),0) -> 10 | F11: 8 | G11: =D11-F11 -> 12 | H11: =IF(G11>=E11,0,MAX(0,E11-G11+ROUND(F11*0.15,0))) -> 0 | I11: 120 | J11: =IF(H11=0,"",H11*I11) | K11: K2 Systems | L11: 5 días | M11: 🟠 ALTA | N11: NO | O11: =IF(H11=0,"N/A",TODAY()+7) -> N/A | P11: PRY-004+PRY-005
A12: BAT-001 | B12: Batería LiFePO4 5kWh | C12: Baterías | D12: =IFERROR(VLOOKUP(A12,'📊 Stock Actual'!$A:$H,8,0),0) -> 7 | E12: =IFERROR(VLOOKUP(A12,'📊 Stock Actual'!$A:$I,9,0),0) -> 2 | F12: 3 | G12: =D12-F12 -> 4 | H12: =IF(G12>=E12,0,MAX(0,E12-G12+ROUND(F12*0.15,0))) -> 0 | I12: 2200 | J12: =IF(H12=0,"",H12*I12) | K12: BYD Europe | L12: 14 días | M12: 🟡 MEDIA | N12: NO | O12: =IF(H12=0,"N/A",TODAY()+7) -> N/A | P12: PRY-005 opcional
A13: PRO-001 | B13: Protección DC 1000V 2P | C13: Protecciones | D13: =IFERROR(VLOOKUP(A13,'📊 Stock Actual'!$A:$H,8,0),0) -> 60 | E13: =IFERROR(VLOOKUP(A13,'📊 Stock Actual'!$A:$I,9,0),0) -> 20 | F13: 5 | G13: =D13-F13 -> 55 | H13: =IF(G13>=E13,0,MAX(0,E13-G13+ROUND(F13*0.15,0))) -> 0 | I13: 45 | J13: =IF(H13=0,"",H13*I13) | K13: Hager Iberia | L13: 3 días | M13: 🟢 NORMAL | N13: NO | O13: =IF(H13=0,"N/A",TODAY()+7) -> N/A | P13: Stock preventivo
A15: IMPORTE TOTAL PEDIDO SUGERIDO | J15: =SUM(J6:J14) -> 0

Sheet 📈 Gráficos
A1: 📈 GRÁFICOS PARA DIRECTIVOS — Visualización ejecutiva
A2: Los gráficos se actualizan automáticamente con los datos de Proyectos, Equipos y Stock.
A5: Tipo Instalación | B5: Nº Proyectos | C5: Facturación (€) | E5: Equipo | F5: Proyectos | G5: Margen Medio % | H5: Incidencias | J5: Mes | K5: Ingresos (€) | L5: Compras (€)
A6: Solar Residencial | B6: =COUNTIF('📋 Proyectos'!$D:$D,A6) -> 2 | C6: =IFERROR(SUMIFS('📋 Proyectos'!$U:$U,'📋 Proyectos'!$D:$D,A6,'📋 Proyectos'!$F:$F,"Completado"),0) -> 0 | E6: Alpha | F6: =COUNTIF('📋 Proyectos'!$E:$E,"Equipo Alpha") -> 3 | G6: =IFERROR(AVERAGEIFS('📋 Proyectos'!$X:$X,'📋 Proyectos'!$E:$E,"Equipo Alpha",'📋 Proyectos'!$F:$F,"Completado"),0) -> 0 | H6: =COUNTIF('⚠️ Incidencias'!$C:$C,"Equipo Alpha") -> 1 | J6: Ene | K6: 8200 | L6: 42680
A7: Solar Industrial | B7: =COUNTIF('📋 Proyectos'!$D:$D,A7) -> 4 | C7: =IFERROR(SUMIFS('📋 Proyectos'!$U:$U,'📋 Proyectos'!$D:$D,A7,'📋 Proyectos'!$F:$F,"Completado"),0) -> 0 | E7: Beta | F7: =COUNTIF('📋 Proyectos'!$E:$E,"Equipo Beta") -> 3 | G7: =IFERROR(AVERAGEIFS('📋 Proyectos'!$X:$X,'📋 Proyectos'!$E:$E,"Equipo Beta",'📋 Proyectos'!$F:$F,"Completado"),0) -> 0 | H7: =COUNTIF('⚠️ Incidencias'!$C:$C,"Equipo Beta") -> 3 | J7: Feb | K7: 32800 | L7: 8200
A8: Aerotermia | B8: =COUNTIF('📋 Proyectos'!$D:$D,A8) -> 2 | C8: =IFERROR(SUMIFS('📋 Proyectos'!$U:$U,'📋 Proyectos'!$D:$D,A8,'📋 Proyectos'!$F:$F,"Completado"),0) -> 0 | E8: Gamma | F8: =COUNTIF('📋 Proyectos'!$E:$E,"Equipo Gamma") -> 2 | G8: =IFERROR(AVERAGEIFS('📋 Proyectos'!$X:$X,'📋 Proyectos'!$E:$E,"Equipo Gamma",'📋 Proyectos'!$F:$F,"Completado"),0) -> 0 | H8: =COUNTIF('⚠️ Incidencias'!$C:$C,"Equipo Gamma") -> 2 | J8: Mar | K8: 0 | L8: 0
A9: Calefacción | B9: =COUNTIF('📋 Proyectos'!$D:$D,A9) -> 1 | C9: =IFERROR(SUMIFS('📋 Proyectos'!$U:$U,'📋 Proyectos'!$D:$D,A9,'📋 Proyectos'!$F:$F,"Completado"),0) -> 0 | E9: Delta | F9: =COUNTIF('📋 Proyectos'!$E:$E,"Equipo Delta") -> 2 | G9: =IFERROR(AVERAGEIFS('📋 Proyectos'!$X:$X,'📋 Proyectos'!$E:$E,"Equipo Delta",'📋 Proyectos'!$F:$F,"Completado"),0) -> 0 | H9: =COUNTIF('⚠️ Incidencias'!$C:$C,"Equipo Delta") -> 1 | J9: Abr | K9: 0 | L9: 0
A10: Mixto Solar+Aero | B10: =COUNTIF('📋 Proyectos'!$D:$D,A10) -> 1 | C10: =IFERROR(SUMIFS('📋 Proyectos'!$U:$U,'📋 Proyectos'!$D:$D,A10,'📋 Proyectos'!$F:$F,"Completado"),0) -> 0 | J10: May | K10: 0 | L10: 0
J11: Jun | K11: 0 | L11: 0
J12: Jul | K12: 0 | L12: 0
J13: Ago | K13: 0 | L13: 0
J14: Sep | K14: 0 | L14: 0
J15: Oct | K15: 0 | L15: 0
J16: Nov | K16: 0 | L16: 0
J17: Dic | K17: 0 | L17: 0

Sheet ⚡ Arquitectura n8n+BQ
A1: ⚡ ARQUITECTURA TÉCNICA — n8n + BigQuery + Power BI
A2: Referencia técnica para IT o consultor. Sin fórmulas — es documentación del sistema completo.
A3: 🏗️ EVOLUCIÓN EN 3 FASES | H3: ID
A4: FASE 1 | C4: HOY — 0-3 meses (~5€/mes) | H4: WF-01 | I4: Stock bajo → Email/WhatsApp compras | J4: Schedule 07:00 diario | K4: 1. Google Sheets: leer hoja Stock Actual 2. Filter: estado contiene BAJO o SIN STOCK 3. IF vacío: stop / continuar 4. Set: formatear lista HTML 5a. Gmail: enviar email con tabla 5b. WhatsApp Business API: mensaje urgente 6. Google Sheets: escribir log en col N | L4: Diario | M4: 🔴 Crítico | N4: Responsable Compras
A5: • Google Sheets como base operativa (sin cambios para el equipo) | H5: WF-02 | I5: Nuevo proyecto → Crear tarea equipo | J5: Google Sheets Trigger (fila nueva) | K5: 1. Google Sheets Trigger: detectar fila nueva en Proyectos 2. Filter: estado = 'En Ejecución' 3. Trello: crear tarjeta en tablero del equipo 4. Gmail: email al jefe de equipo con detalles 5. Google Sheets: leer plantilla de materiales 6. BigQuery: INSERT en tabla proyectos | L5: Tiempo real | M5: 🔴 Crítico | N5: Equipo asignado
A6: • n8n self-hosted en VPS Hetzner CX11 = 4.51€/mes | H6: WF-03 | I6: Incidencia nueva → Alerta inmediata | J6: Google Sheets Trigger (fila nueva) | K6: 1. Google Sheets Trigger: fila nueva en Incidencias 2. Lookup: buscar jefe equipo en tabla equipos 3. WhatsApp Business: mensaje urgente al jefe 4. Gmail: email detallado con datos incidencia 5. Trello: añadir comentario en tarjeta proyecto 6. BigQuery: INSERT en tabla incidencias | L6: Tiempo real | M6: 🔴 Crítico | N6: Jefe de equipo
A7: • Workflows activos: alertas stock, alertas incidencias, informe semanal | H7: WF-04 | I7: Proyecto completado → Archivar en BQ | J7: Google Sheets Trigger (col F) | K7: 1. Google Sheets Trigger: col F cambia a 'Completado' 2. Google Sheets: leer fila completa con todos los datos 3. HTTP Request: calcular margen final 4. BigQuery: INSERT proyectos_historico 5. BigQuery: INSERT costes_detallados 6. Gmail: resumen de margen a dirección | L7: Tiempo real | M7: 🟠 Alta | N7: Dirección / Contabilidad
A8: • Power BI Desktop gratuito conectado a Google Sheets | H8: WF-05 | I8: Garantías próximas → Comercial | J8: Schedule lunes 08:30 | K8: 1. Google Sheets: leer Garantías y Mantenimiento 2. Filter: dias_para_vencer <= 90 3. IF sin resultados: stop 4. Set: construir tabla HTML con clientes 5. Gmail: email a comercial con lista 6. HubSpot/CRM: crear tarea de seguimiento 7. Sheets: marcar columna 'Alerta enviada' | L8: Semanal | M8: 🟠 Alta | N8: Comercial
A9: • BigQuery creado pero solo recibe snapshots diarios del stock | H9: WF-06 | I9: Presupuesto → Generar PDF y enviar | J9: Google Sheets Trigger (estado) | K9: 1. Sheets Trigger: estado cambia a 'En Ejecución' 2. Google Sheets: leer todos los datos proyecto 3. HTTP POST: API Carbone.io con template Word 4. HTTP GET: descargar PDF generado 5. Google Drive: guardar en carpeta /Presupuestos/Cliente 6. Gmail: enviar PDF al cliente con mensaje personalizado | L9: Tiempo real | M9: 🟠 Alta | N9: Cliente / Comercial
H10: WF-07 | I10: Margen bajo → Alerta dirección | J10: Schedule 12:00 diario | K10: 1. Google Sheets: leer proyectos con estado 'En Ejecución' 2. Calcular: coste_actual / precio_venta (margen provisional) 3. Filter: margen < 15% 4. IF vacío: stop 5. Gmail: email urgente a dirección con proyectos en riesgo 6. Slack/Teams: mensaje en canal #alertas-financieras 7. Sheets: colorear fila en rojo | L10: Diario | M10: 🟠 Alta | N10: Dirección
A11: FASE 2 | C11: MEDIO PLAZO — 3-9 meses (~30€/mes) | H11: WF-08 | I11: Informe semanal automático | J11: Schedule viernes 17:00 | K11: 1. BigQuery: query KPIs semana (proyectos, margen, incidencias) 2. Google Sheets: leer datos stock crítico 3. Calcular: comparativa con semana anterior en BQ 4. HTTP POST: API Carbone.io para PDF ejecutivo 5. Gmail: enviar a lista VIPs (dirección, socios) 6. Power BI REST API: forzar refresh del dataset 7. BigQuery: INSERT en tabla reportes_semanales | L11: Semanal | M11: 🟡 Media | N11: Dirección / Socios
A12: • BigQuery recibe TODOS los movimientos en tiempo real vía n8n
A13: • Power BI Service web (9.99€/usuario) — dashboards online en el móvil
A14: • n8n genera PDFs de presupuestos automáticamente (API Carbone.io)
A15: • Alertas WhatsApp Business por incidencias y garantías
A16: • n8n crea tareas en Trello/Notion al asignar proyectos a equipos
A18: FASE 3 | C18: LARGO PLAZO — 9-18 meses (~150€/mes)
A19: • Migración a Odoo Community (ERP open source, servidor ~20€/mes)
A20: • n8n reconecta a Odoo — Power BI no cambia absolutamente nada
A21: • Técnicos usan app móvil Odoo para registrar horas y materiales en campo
A22: • Firma digital de presupuestos con Odoo Sign
A23: • Facturación automática al cambiar estado proyecto a 'Completado'
A25: 🗄️ BIGQUERY — SCHEMA DE TABLAS (copiar en BQ Console)
A26: Tabla | B26: Descripción | C26: Schema (campos y tipos)
A27: proyectos_historico | B27: Todos los proyectos completados. Alimentado por WF-04. | C27: proyecto_id STRING NOT NULL, cliente STRING, tipo_instalacion STRING, equipo STRING, estado STRING, fecha_inicio DATE, fecha_fin DATE, precio_venta FLOAT64, coste_material FLOAT64, coste_mo FLOAT64, coste_total FLOAT64, margen_bruto FLOAT64, pct_margen FLOAT64, n_incidencias INT64, timestamp_sync TIMESTAMP
A28: movimientos_stock | B28: Histórico completo de entradas y salidas de almacén. Alimentado por WF diario. | C28: mov_id STRING NOT NULL, tipo STRING, -- ENTRADA/SALIDA ref_producto STRING, descripcion STRING, categoria STRING, cantidad FLOAT64, precio_unitario FLOAT64, importe FLOAT64, fecha DATE, proyecto_id STRING, responsable STRING, timestamp_sync TIMESTAMP
A29: incidencias | B29: Registro de todas las incidencias. Alimentado por WF-03. | C29: inc_id STRING NOT NULL, proyecto_id STRING, equipo STRING, tecnico STRING, fecha DATE, tipo STRING, descrip STRING, horas_extra FLOAT64, coste_extra FLOAT64, estado STRING, timestamp_sync TIMESTAMP
A30: horas_mo | B30: Registro de mano de obra. Alimentado por WF diario. | C30: mov_id STRING NOT NULL, proyecto_id STRING, equipo STRING, tecnico STRING, fecha DATE, concepto STRING, horas FLOAT64, coste FLOAT64, timestamp_sync TIMESTAMP
A31: stock_daily_snapshot | B31: Foto diaria del stock para evolución histórica en Power BI. | C31: ref_producto STRING, descripcion STRING, categoria STRING, stock_qty FLOAT64, valor_coste FLOAT64, estado STRING, fecha DATE NOT NULL, timestamp_sync TIMESTAMP
A32: kpis_semanales | B32: KPIs consolidados por semana. Alimentado por WF-08. | C32: semana_inicio DATE NOT NULL, proyectos_completados INT64, facturacion FLOAT64, coste_total FLOAT64, margen_bruto FLOAT64, pct_margen FLOAT64, n_incidencias INT64, stock_valor FLOAT64, timestamp_sync TIMESTAMP
A35: 🖥️ INSTALACIÓN n8n EN 30 MINUTOS (self-hosted)
A36: 1. VPS | B36: Hetzner Cloud → CX11: 1vCPU 2GB RAM = 4.51€/mes Ubuntu 22.04 LTS. IP fija incluida.
A37: 2. Docker | B37: Instalar Docker en el servidor: | C37: curl -fsSL https://get.docker.com | sh sudo usermod -aG docker $USER newgrp docker
A38: 3. n8n | B38: Lanzar n8n con Docker Compose (recomendado sobre docker run): | C38: version: '3.8' services: n8n: image: n8nio/n8n restart: unless-stopped ports: - 5678:5678 environment: - N8N_BASIC_AUTH_ACTIVE=true - N8N_BASIC_AUTH_USER=admin - N8N_BASIC_AUTH_PASSWORD=PASSWORD_SEGURO - WEBHOOK_URL=https://n8n.tuempresa.com volumes: - ~/.n8n:/home/node/.n8n
A39: 4. Dominio + HTTPS | B39: Apuntar subdominio n8n.tuempresa.com a la IP del VPS. Instalar Nginx + Certbot para HTTPS gratuito. | C39: sudo apt install nginx certbot python3-certbot-nginx sudo certbot --nginx -d n8n.tuempresa.com
A40: 5. Credenciales | B40: En n8n → Settings → Credentials: • Google Sheets: OAuth2 (Google Cloud Console) • BigQuery: Service Account JSON • Gmail: OAuth2 • WhatsApp Business: token de Meta for Developers • Power BI: OAuth2 (Azure App Registration) | C40: # Tiempo estimado total: 45-60 minutos # Coste total mensual: ~5€

Sheet 📋 Instrucciones
A1: 📋 GUÍA DE USO — Sistema de Control de Inventario
A3: 🗂️ ESTRUCTURA DEL ARCHIVO
A4: 📦 Maestro Productos | B4: Base de datos de todos los productos. Aquí se añaden nuevos artículos, se actualizan precios y datos maestros. NO borrar ni cambiar los códigos REF.
A5: 📊 Stock Actual | B5: Vista automática del stock. Esta hoja NO se edita manualmente — se calcula sola con las entradas y salidas. Solo hay que actualizar el 'Stock Inicial' al empezar a usar el sistema.
A6: 📥 Entradas | B6: Registrar aquí cada entrada de material: compras a proveedor, devoluciones de obra, ajustes positivos. Rellenar: REF, Tipo, Cantidad, Fecha, Proveedor y Nº Albarán.
A7: 📤 Salidas | B7: Registrar aquí cada salida: material enviado a obra, ventas directas, mermas. Rellenar: REF, Tipo, Cantidad, Fecha, Obra/Cliente y Nº Pedido.
A8: 🎯 Dashboard | B8: Resumen ejecutivo automático: KPIs, alertas de stock bajo y resumen financiero. Solo lectura.
A10: 👥 ROLES Y PERMISOS (configurar en Google Sheets)
A11: Personal de Almacén | B11: Acceso de edición solo a las hojas '📥 Entradas' y '📤 Salidas'. Instrucción: rellenar col A (Nº Mov. correlativo), col B (REF exacta), col D (Tipo), col E (Cantidad), col F (Precio), col H (Fecha), col I (Destino/Proveedor), col J (Albarán), col K (Responsable).
A12: Contabilidad / Dirección | B12: Acceso completo a todas las hojas. Verificar periódicamente el Dashboard y cotejar los importes con las facturas.
A14: ⚠️ REGLAS IMPORTANTES
A15: Códigos REF | B15: Los códigos REF son la clave del sistema. Deben coincidir exactamente entre el Maestro, Entradas y Salidas. No usar espacios extra ni caracteres especiales.
A16: Stock Inicial | B16: Al implantar el sistema, actualizar la columna E de '📊 Stock Actual' con el inventario físico real. Hacer un conteo físico antes de empezar.
A17: Numeración | B17: Usar numeración correlativa en Nº Mov.: E-001, E-002... para entradas y S-001, S-002... para salidas. Facilita las auditorías.
A18: Fechas | B18: Usar siempre formato DD/MM/YYYY. En Google Sheets escribir directamente la fecha y el sistema la reconoce.
A19: Nuevo producto | B19: Añadir la nueva referencia en '📦 Maestro Productos' primero. Luego copiar una fila existente en '📊 Stock Actual' y actualizar la fórmula de referencia.
A21: 💡 CONSEJOS PARA GOOGLE SHEETS
A22: Acceso móvil | B22: El personal de almacén puede usar la app de Google Sheets en el móvil para registrar entradas/salidas en tiempo real desde la nave.
A23: Notificaciones | B23: En Google Sheets: Herramientas > Notificaciones > configurar alertas por email cuando se modifique la hoja.
A24: Proteger hojas | B24: En Google Sheets: clic derecho en pestaña > Proteger hoja > limitar edición por usuario. Proteger 'Maestro', 'Stock' y 'Dashboard'.
A25: Historial | B25: Google Sheets guarda historial completo de cambios. Si alguien borra algo por error: Archivo > Historial de versiones > Ver historial.
A26: Filtros | B26: Usar Datos > Crear un filtro en las hojas de Entradas y Salidas para buscar por fecha, referencia, tipo, etc.
